Workbook

Sheet Resumo
L1: Entradas nas últimas semanas | Q1: Histórico Atendimento | U1: Mensagens Transacionadas
B2: Mês Ref | C2: Qted | D2: Total Emitido (R$) | E2: Total Pago (R$) | F2: Valor em Acordo | G2: Valor Inadimplente | H2: % inadimplência | I2: % inadimplência anterior gestão HUBE | Q2: Ano | R2: Mês | S2: Quantidade | U2: Mês | V2: Entradas | W2: Saídas
B3: 45658 | C3: 84 | D3: 19964.24 | E3: 19059.44 | F3: 0 | G3: 904.8 | H3: 0.045321034 | I3: 0.12 | Q3: 2025 | R3: Agosto | S3: 135 | U3: Agosto | V3: 578 | W3: 662
B4: 45689 | C4: 50 | D4: 16003.59 | E4: 15264.88 | F4: 0 | G4: 738.71 | H4: 0.046159018 | I4: 0.11 | Q4: 2025 | R4: Setembro | S4: 150 | U4: Setembro | V4: 1183 | W4: 1533
B5: 45717 | C5: 55 | D5: 17915 | E5: 17007.83 | F5: 0 | G5: 907.17 | H5: 0.050637455 | I5: 0.3 | Q5: 2025 | R5: Outubro | S5: 78 | U5: Outubro | V5: 671 | W5: 909
B6: 45748 | C6: 86 | D6: 18900.91 | E6: 16189.3 | F6: 175.21 | G6: 2536.4 | H6: 0.1341946 | I6: 0.32
B7: 45778 | C7: 83 | D7: 16645.9 | E7: 14193.639 | F7: 0 | G7: 2452.261 | H7: 0.14731922 | I7: 0.4
B8: 45809 | C8: 63 | D8: 9822.37 | E8: 9532.5733 | F8: 0 | G8: 289.79667 | H8: 0.029503742
B9: 45839 | C9: 75 | D9: 12120.21 | E9: 12060.14 | F9: 161.56 | G9: -101.49 | H9: 0
B10: 45870 | C10: 78 | D10: 14372.97 | E10: 14030.1 | F10: 172.03 | G10: 170.84 | H10: 0.0118862
B11: 45901 | C11: 79 | D11: 18122.97 | E11: 17328.501 | F11: 0 | G11: 794.46947 | H11: 0.043837708
B12: 45931 | C12: 85 | D12: 23671.21 | E12: 22313.22 | F12: 0 | G12: 1357.99 | H12: 0.057368846
B13: 45962 | C13: 87 | D13: 28544.62 | E13: 18614.41 | F13: 0 | G13: 9930.21 | H13: 0.34788377
B14: Total Geral | C14: 825 | D14: 196083.99 | E14: 175594.03 | F14: 508.8 | G14: 8692.9571 | H14: 0.056539886
N42: Etapa | O42: Tempo Semanal | P42: Responsável
N43: Atendimento | O43: 3 horas | P43: Isabella
N44: Faturamento | O44: 0,5 horas | P44: Isabella
N45: Cobrança | O45: 5 horas | P45: Adriano
N46: Report EGS | O46: 1 hora | P46: Carol
N47: Total | O47: 9,5 horas

Sheet base
A2: INSTALAÇÃO | B2: NOME COMPLETO OU RAZÃO SOCIAL | C2: CNPJ | D2: DISTRIBUIDORA | E2: STATUS RATEIO | F2: STATUS DE CLIENTE | G2: MOTIVO RETIRADA | H2: DATA RETIRADA DE RATEIO | I2: E-MAIL | J2: TELEFONE | K2: FORNECIMENTO | L2: DESCONTO CONTRATADO | M2: REGIÃO | N2: CEP | O2: UF | P2: ENDEREÇO COMPLETO | Q2: CONS. DISPONÍVEL KWH | R2: CONSUMO ALVO | S2: BOLETOS ATRASADOS
A3: 10/1017804-4 | B3: IGREJA DO EVANGELHO QUADRANGULAR | C3: 62.955.505/8789-87 | D3: ENERGISA MS | E3: ACOMPANHAR CRÉDITO | F3: ATIVO | G3: Inadimplência | H3: 45954 | I3: maretoliedu@hotmail.com | J3: 6792157907 | K3: BIFÁSICO | L3: 0.25 | M3: 319 | O3: MS | P3: RUA AIMORE DE OLIVEIRA LIMA, 835 - 14.094.85.107001 - 79920000 | Q3: 255 | R3: 325 | S3: =COUNTIFS(Faturamento!B:B,Base_Clientes[[#This Row],[INSTALAÇÃO]],Faturamento!V:V,"Atrasado") -> 2
A4: 10/10232-7 | B4: IGREJA DO EVANGELHO QUADRANGULAR | C4: 62.955.505/3932-07 | D4: ENERGISA MS | E4: APTO RATEIO | F4: ATIVO | I4: katiaconceicaogomes2020@gmail.com | J4: 67 996415566 | K4: BIFÁSICO | L4: 0.25 | M4: 302 | O4: MS | P4: RUA ONZE S/N Q 74 L 22 10.002.13.434000 - NOVA AQUIDAUANA, CEP 79200000 - AQUIDAUANA / MS | Q4: 99.833333 | R4: 99.833333 | S4: =COUNTIFS(Faturamento!B:B,Base_Clientes[[#This Row],[INSTALAÇÃO]],Faturamento!V:V,"Atrasado") -> 0
A5: 10/1035655-8 | B5: IGREJA DO EVANGELHO QUADRANGULAR | C5: 62.955.505/1822-57 | D5: ENERGISA MS | E5: APTO RATEIO | F5: ATIVO | I5: auxiliar.cedms@gmail.com | J5: 67996135721 | K5: TRIFÁSICO | L5: 0.25 | M5: 319 | O5: MS | P5: RUA ANTONIO AMARO DE MATTOS 5422 CX 02 07.010.26.205001 - VILA ROSA, CEP 79831130 - DOURADOS / MS | Q5: 453.58333 | R5: 453.58333 | S5: =COUNTIFS(Faturamento!B:B,Base_Clientes[[#This Row],[INSTALAÇÃO]],Faturamento!V:V,"Atrasado") -> 0
A6: 10/104720-8 | B6: IGREJA DO EVANGELHO QUADRANGULAR | C6: 62.955.505/0914-56 | D6: ENERGISA MS | E6: ACOMPANHAR CRÉDITO | F6: INATIVO | G6: Solicitação de distrato | I6: auxiliar.cedms@gmail.com | J6: 67991767866 | L6: 0.25 | M6: 306 | O6: MS | Q6: 136 | R6: 136 | S6: =COUNTIFS(Faturamento!B:B,Base_Clientes[[#This Row],[INSTALAÇÃO]],Faturamento!V:V,"Atrasado") -> 0
A7: 10/1081489-5 | B7: IGREJA DO EVANGELHO QUADRANGULAR | C7: 62.955.505/0169-18 | D7: ENERGISA MS | E7: APTO RATEIO | F7: ATIVO | I7: regiao351@gmail.com | J7: 67996446178 | K7: BIFÁSICO | L7: 0.25 | M7: 351 | O7: MS | P7: RUA PRUDENTE DE MORAES ALTO MARACAJU CEP 79150000 - MARACAJU / MS | Q7: 501.83333 | R7: 547.45455 | S7: =COUNTIFS(Faturamento!B:B,Base_Clientes[[#This Row],[INSTALAÇÃO]],Faturamento!V:V,"Atrasado") -> 1
A8: 10/109074-5 | B8: IGREJA DO EVANGELHO QUADRANGULAR | C8: 62.955.505/0001-67 | D8: ENERGISA MS | E8: ACOMPANHAR CRÉDITO | F8: ATIVO | G8: Inadimplência | H8: 45954 | I8: auxiliar.cedms@gmail.com | J8: 67 91751433 | K8: BIFÁSICO | L8: 0.25 | M8: 319 | O8: MS | P8: RUA QUINZE DE NOVEMBRO 2180 - CENTRO CEP 79940000 - CAARAPO / MS | Q8: 224.41667 | R8: 244.81818 | S8: =COUNTIFS(Faturamento!B:B,Base_Clientes[[#This Row],[INSTALAÇÃO]],Faturamento!V:V,"Atrasado") -> 6
A9: 10/1117293-9 | B9: IGREJA DO EVANGELHO QUADRANGULAR | C9: 62.955.505/8921-14 | D9: ENERGISA MS | E9: APTO RATEIO | F9: ATIVO | I9: pastoreliasmn@hotmail.com | J9: 67999516782 | K9: TRIFÁSICO | L9: 0.25 | M9: 362 | O9: MS | P9: AVENIDA ANTONIO JOAQUIM DE MOURA ANDRADE 2141 10 041 07 522500 - CENTRO CEP 79750000 - NOVA ANDRADINA / MS | Q9: 178.41667 | R9: 178.41667 | S9: =COUNTIFS(Faturamento!B:B,Base_Clientes[[#This Row],[INSTALAÇÃO]],Faturamento!V:V,"Atrasado") -> 1
A10: 10/1130988-7 | B10: IGREJA DO EVANGELHO QUADRANGULAR | C10: 62.955.505/0408-94 | D10: ENERGISA MS | E10: APTO RATEIO | F10: ATIVO | I10: regiao371@gmail.com | J10: 67992637973 | K10: BIFÁSICO | L10: 0.25 | M10: 371 | O10: MS | P10: RUA CAPITAO CANTALICE S/N CENTRO CEP 79280000 - PORTO MURTINHO / MS | Q10: 218.66667 | R10: 238.54545 | S10: =COUNTIFS(Faturamento!B:B,Base_Clientes[[#This Row],[INSTALAÇÃO]],Faturamento!V:V,"Atrasado") -> 0
A11: 10/113971-6 | B11: IGREJA DO EVANGELHO QUADRANGULAR | C11: 62.955.505/0156-01 | D11: ENERGISA MS | E11: ACOMPANHAR CRÉDITO | F11: INATIVO | G11: Solicitação de distrato | I11: auxiliar.cedms@gmail.com | J11: 67996575782 | K11: TRIFÁSICO | L11: 0.25 | M11: 319 | O11: MS | P11: RUA CARLOS CHAGAS 1092 05.026.05.081000 - JARDIM SAO PAULO, CEP 79700000 - FATIMA DO SUL / MS | Q11: 236.08333 | R11: 236.08333 | S11: =COUNTIFS(Faturamento!B:B,Base_Clientes[[#This Row],[INSTALAÇÃO]],Faturamento!V:V,"Atrasado") -> 0
A12: 10/1184751-4 | B12: IGREJA DO EVANGELHO QUADRANGULAR | C12: 62.955.505/1490-47 | D12: ENERGISA MS | E12: APTO RATEIO | F12: ATIVO | I12: auxiliar.cedms@gmail.com | J12: 67 96034976 | K12: TRIFÁSICO | L12: 0.25 | M12: 319 | O12: MS | P12: RUA DOM PEDRO I 1135 07.010.45.317001 - JARDIM GUANABARA, CEP 79833090 - DOURADOS / MS | Q12: 182.25 | R12: 182.25 | S12: =COUNTIFS(Faturamento!B:B,Base_Clientes[[#This Row],[INSTALAÇÃO]],Faturamento!V:V,"Atrasado") -> 0
A13: 10/1266128-6 | B13: IGREJA DO EVANGELHO QUADRANGULAR | C13: 62.955.505/3793-95 | D13: ENERGISA MS | E13: APTO RATEIO | F13: ATIVO | I13: auxiliar.cedms@gmail.com | J13: 67991306665 | K13: TRIFÁSICO | L13: 0.25 | M13: 306 | O13: MS | P13: RUA MARACANI 439 PARQUE DOS NOVOS ESTADOS CEP 79034280 - CAMPO GRANDE / MS | Q13: 365 | R13: 398.18182 | S13: =COUNTIFS(Faturamento!B:B,Base_Clientes[[#This Row],[INSTALAÇÃO]],Faturamento!V:V,"Atrasado") -> 0
A14: 10/127464-6 | B14: IGREJA DO EVANGELHO QUADRANGULAR | C14: 62.955.505/3311-98 | D14: ENERGISA MS | E14: APTO RATEIO | F14: ATIVO | I14: mariza.ieq@gmail.com | J14: 67996150274 | K14: TRIFÁSICO | L14: 0.25 | M14: 360 | O14: MS | P14: AVENIDA MATO GROSSO DO SUL 1466 CENTRO CEP 79400000 - COXIM / MS | Q14: 432.33333 | R14: 471.63636 | S14: =COUNTIFS(Faturamento!B:B,Base_Clientes[[#This Row],[INSTALAÇÃO]],Faturamento!V:V,"Atrasado") -> 0
A15: 10/1288241-1 | B15: IGREJA DO EVANGELHO QUADRANGULAR | C15: 62.955.505/3358-51 | D15: ENERGISA MS | E15: APTO RATEIO | F15: ATIVO | I15: auxiliar.cedms@gmail.com | J15: 67991133770 | K15: TRIFÁSICO | L15: 0.25 | M15: 306 | O15: MS | P15: AVENIDA TAMANDARE 1036 VILA PLANALTO CEP 79009790 - CAMPO GRANDE / MS | Q15: 192.08333 | R15: 209.54545 | S15: =COUNTIFS(Faturamento!B:B,Base_Clientes[[#This Row],[INSTALAÇÃO]],Faturamento!V:V,"Atrasado") -> 0
A16: 10/129490-9 | B16: IGREJA DO EVANGELHO QUADRANGULAR | C16: 62.955.505/4051-40 | D16: ENERGISA MS | E16: ACOMPANHAR CRÉDITO | F16: ATIVO | G16: Inadimplência | H16: 45954 | I16: regiao351@gmail.com | J16: 67996446178 | K16: BIFÁSICO | L16: 0.25 | M16: 351 | O16: MS | P16: RUA JUVIANO MEDEIROS 1239 CENTRO CEP 79130000 - RIO BRILHANTE / MS | Q16: 226.16667 | R16: 246.72727 | S16: =COUNTIFS(Faturamento!B:B,Base_Clientes[[#This Row],[INSTALAÇÃO]],Faturamento!V:V,"Atrasado") -> 1
A17: 10/135237-6 | B17: IGREJA DO EVANGELHO QUADRANGULAR | C17: 62.955.505/0800-98 | D17: ENERGISA MS | E17: APTO RATEIO | F17: ATIVO | I17: regiao351@gmail.com | J17: 67996446178 | K17: TRIFÁSICO | L17: 0.25 | M17: 351 | O17: MS | P17: RUA ROSALVO FRAGA SANTOS 60 05.031.05.383000 - VILA PRATEADA, CEP 79150000 - MARACAJU / MS | Q17: 134.36364 | R17: 134.36364 | S17: =COUNTIFS(Faturamento!B:B,Base_Clientes[[#This Row],[INSTALAÇÃO]],Faturamento!V:V,"Atrasado") -> 0
A18: 10/13786-9 | B18: IGREJA DO EVANGELHO QUADRANGULAR | C18: 62.955.505/1975-21 | D18: ENERGISA MS | E18: APTO RATEIO | F18: ATIVO | I18: regiao.357.25@gmail.com | J18: 67996266684 | K18: BIFÁSICO | L18: 0.25 | M18: 357 | O18: MS | P18: RUA MARECHAL DEODORO 118 DOM BOSCO CEP 79333080 - CORUMBA / MS | Q18: 255.16667 | R18: 278.36364 | S18: =COUNTIFS(Faturamento!B:B,Base_Clientes[[#This Row],[INSTALAÇÃO]],Faturamento!V:V,"Atrasado") -> 1
A19: 10/142353-2 | B19: IGREJA DO EVANGELHO QUADRANGULAR | C19: 62.955.505/1138-75 | D19: ENERGISA MS | E19: APTO RATEIO | F19: ATIVO | I19: odpto61@hotmail.com | J19: 67992899434 | K19: BIFÁSICO | L19: 0.25 | M19: 358 | O19: MS | P19: RUA ANTONIO JOAO 2547 CENTRO CEP 79904668 - PONTA PORA / MS | Q19: 412.33333 | R19: 449.81818 | S19: =COUNTIFS(Faturamento!B:B,Base_Clientes[[#This Row],[INSTALAÇÃO]],Faturamento!V:V,"Atrasado") -> 0
A20: 10/1433087-2 | B20: IGREJA DO EVANGELHO QUADRANGULAR | C20: 62.955.505/4194-43 | D20: ENERGISA MS | E20: ACOMPANHAR CRÉDITO | F20: INATIVO | G20: Solicitação de distrato | I20: scr_prmarcal@hotmail.com | J20: 67 91285460 | K20: TRIFÁSICO | L20: 0.25 | M20: 331 | O20: MS | Q20: 235.08333 | R20: 235.08333 | S20: =COUNTIFS(Faturamento!B:B,Base_Clientes[[#This Row],[INSTALAÇÃO]],Faturamento!V:V,"Atrasado") -> 0
A21: 10/150263-2 | B21: IGREJA DO EVANGELHO QUADRANGULAR | C21: 62.955.505/0914-56 | D21: ENERGISA MS | E21: RESCINDIDO | F21: INATIVO | G21: Solicitação de distrato | I21: região358ms@gmail.com | J21: 67992337953 | K21: MONOFÁSICO | L21: 0.25 | M21: 358 | O21: MS | Q21: 162 | R21: 162 | S21: =COUNTIFS(Faturamento!B:B,Base_Clientes[[#This Row],[INSTALAÇÃO]],Faturamento!V:V,"Atrasado") -> 1
A22: 10/15297-5 | B22: IGREJA DO EVANGELHO QUADRANGULAR | C22: 62.955.505/3124-87 | D22: ENERGISA MS | E22: APTO RATEIO | F22: ATIVO | I22: regiao.357.25@gmail.com | J22: 67996266684 | K22: TRIFÁSICO | L22: 0.25 | M22: 357 | O22: MS | P22: RUA REPUBLICA DA BOLIVIA, 32 DOM BOSCO CORUMBA / MS | Q22: 453.91667 | R22: 495.18182 | S22: =COUNTIFS(Faturamento!B:B,Base_Clientes[[#This Row],[INSTALAÇÃO]],Faturamento!V:V,"Atrasado") -> 0
A23: 10/1548741-6 | B23: IGREJA DO EVANGELHO QUADRANGULAR | C23: 62.955.505/0847-51 | D23: ENERGISA MS | E23: APTO RATEIO | F23: ATIVO | I23: ieqreg349cassi@gmail.com | J23: 67 81355403 | K23: MONOFÁSICO | L23: 0.25 | M23: 349 | O23: MS | P23: RUA JOSE AGI 651 12.014.07.803500 - JARDIM AMERICA CEP 79500000 - PARANAIBA / MS | Q23: 156.25 | R23: 156.25 | S23: =COUNTIFS(Faturamento!B:B,Base_Clientes[[#This Row],[INSTALAÇÃO]],Faturamento!V:V,"Atrasado") -> 1
A24: 10/156956-5 | B24: IGREJA DO EVANGELHO QUADRANGULAR | C24: 62.955.505/0153-50 | D24: ENERGISA MS | E24: APTO RATEIO | F24: ATIVO | I24: quadrangular994@gmail.com | J24: 67 998338301 | K24: TRIFÁSICO | L24: 0.25 | M24: 994 | O24: MS | P24: RUA GENERAL CAMARA 561 14.036.03.163000 - CENTRO, CEP 79990000 - AMAMBAI / MS | Q24: 362.41667 | R24: 362.41667 | S24: =COUNTIFS(Faturamento!B:B,Base_Clientes[[#This Row],[INSTALAÇÃO]],Faturamento!V:V,"Atrasado") -> 0
A25: 10/162736-3 | B25: IGREJA DO EVANGELHO QUADRANGULAR | C25: 62.955.505/1973-60 | D25: ENERGISA MS | E25: ACOMPANHAR CRÉDITO | F25: ATIVO | G25: Inadimplência | H25: 45954 | I25: mariza.ieq@gmail.com | J25: 67996150274 | K25: TRIFÁSICO | L25: 0.25 | M25: 360 | O25: MS | P25: RUA SANTOS DUMONT 310 15.037.01.489000 - CENTRO CEP 79480000 - RIO VERDE DE MATO GROSSO / MS | Q25: 185.66667 | R25: 185.66667 | S25: =COUNTIFS(Faturamento!B:B,Base_Clientes[[#This Row],[INSTALAÇÃO]],Faturamento!V:V,"Atrasado") -> 5
A26: 10/1672452-8 | B26: IGREJA DO EVANGELHO QUADRANGULAR | C26: 62.955.505/0172-13 | D26: ENERGISA MS | E26: APTO RATEIO | F26: ATIVO | I26: regiao371@gmail.com | J26: 67992637973 | K26: TRIFÁSICO | L26: 0.25 | M26: 371 | O26: MS | P26: RUA N SRA DA PENHA, 540, CENTRO, BONITO-MS | Q26: 418.16667 | R26: 418.16667 | S26: =COUNTIFS(Faturamento!B:B,Base_Clientes[[#This Row],[INSTALAÇÃO]],Faturamento!V:V,"Atrasado") -> 0
A27: 10/1674177-9 | B27: IGREJA DO EVANGELHO QUADRANGULAR | C27: 62.955.505/0161-60 | D27: ENERGISA MS | E27: APTO RATEIO | F27: ATIVO | I27: 3ieqant302@gmail.com | J27: 6784548587 | K27: TRIFÁSICO | L27: 0.25 | M27: 302 | O27: MS | P27: RUA JOAO LEITE RIBEIRO 1636 CENTRO CEP 79210000 - ANASTACIO / MS | Q27: 218.66667 | R27: 393 | S27: =COUNTIFS(Faturamento!B:B,Base_Clientes[[#This Row],[INSTALAÇÃO]],Faturamento!V:V,"Atrasado") -> 0
A28: 10/1695011-5 | B28: IGREJA DO EVANGELHO QUADRANGULAR | C28: 62.955.505/4612-10 | D28: ENERGISA MS | E28: APTO RATEIO | F28: ATIVO | I28: auxiliar.cedms@gmail.com | J28: 67991767866 | K28: TRIFÁSICO | L28: 0.25 | M28: 306 | O28: MS | P28: RUA JOSE RICARTES DE OLIVEIRA, 56, SANTO ANDRE, RIBAS DO RIO PARDO | Q28: 511.41667 | R28: 511.41667 | S28: =COUNTIFS(Faturamento!B:B,Base_Clientes[[#This Row],[INSTALAÇÃO]],Faturamento!V:V,"Atrasado") -> 0
A29: 10/1698130-0 | B29: IGREJA DO EVANGELHO QUADRANGULAR | C29: 62.955.505/4612-10 | D29: ENERGISA MS | E29: APTO RATEIO | F29: ATIVO | I29: auxiliar.cedms@gmail.com | J29: 67991767866 | K29: TRIFÁSICO | L29: 0.25 | M29: 306 | O29: MS | P29: RUA JOSE RICARTES DE OLIVEIRA, 56, SANTO ANDRE, RIBAS DO RIO PARDO | Q29: 279.08333 | R29: 279.08333 | S29: =COUNTIFS(Faturamento!B:B,Base_Clientes[[#This Row],[INSTALAÇÃO]],Faturamento!V:V,"Atrasado") -> 0
A30: 10/175073-6 | B30: IGREJA DO EVANGELHO QUADRANGULAR | C30: 62.955.505/1344-49 | D30: ENERGISA MS | E30: APTO RATEIO | F30: ATIVO | I30: pastoreliasmn@hotmail.com | J30: 67999516782 | K30: BIFÁSICO | L30: 0.25 | M30: 362 | O30: MS | P30: RUA MIGUEL MARCHETTI 149 ITAPOA CEP 79740000 - IVINHEMA / MS | Q30: 129.08333 | R30: 140.81818 | S30: =COUNTIFS(Faturamento!B:B,Base_Clientes[[#This Row],[INSTALAÇÃO]],Faturamento!V:V,"Atrasado") -> 1
A31: 10/18015-8 | B31: IGREJA DO EVANGELHO QUADRANGULAR | C31: 62.955.505/0160-80 | D31: ENERGISA MS | E31: APTO RATEIO | F31: ATIVO | I31: regiao.357.25@gmail.com | J31: 67996266684 | K31: TRIFÁSICO | L31: 0.25 | M31: 357 | O31: MS | P31: RUA JOAQUIM MURTINHO, 72, CENTRO, CORUMBA-MS | Q31: 958.25 | R31: 958.25 | S31: =COUNTIFS(Faturamento!B:B,Base_Clientes[[#This Row],[INSTALAÇÃO]],Faturamento!V:V,"Atrasado") -> 1
A32: 10/191945-5 | B32: IGREJA DO EVANGELHO QUADRANGULAR | C32: 62.955.505/2157-91 | D32: ENERGISA MS | E32: APTO RATEIO | F32: ATIVO | I32: ieqreg349cassi@gmail.com | J32: 67 81355403 | K32: TRIFÁSICO | L32: 0.25 | M32: 349 | O32: MS | P32: RUA GOIAS, 1000, CENTRO, CASSILANDIA-MS | Q32: 802.5 | R32: 802.5 | S32: =COUNTIFS(Faturamento!B:B,Base_Clientes[[#This Row],[INSTALAÇÃO]],Faturamento!V:V,"Atrasado") -> 0
A33: 10/1939035-0 | B33: IGREJA DO EVANGELHO QUADRANGULAR | C33: 62.955.505/4194-43 | D33: ENERGISA MS | E33: APTO RATEIO | F33: ATIVO | I33: scr_prmarcal@hotmail.com | J33: 67 91285460 | K33: BIFÁSICO | L33: 0.25 | M33: 331 | O33: MS | P33: RUA NOVE, 121 / QD E LT 1B - RESIDENCIAL MODELO II - BATAGUASSU/MS | Q33: 372.25 | R33: 372.25 | S33: =COUNTIFS(Faturamento!B:B,Base_Clientes[[#This Row],[INSTALAÇÃO]],Faturamento!V:V,"Atrasado") -> 0
A34: 10/202838-9 | B34: IGREJA DO EVANGELHO QUADRANGULAR | C34: 62.955.505/0164-03 | D34: ENERGISA MS | E34: APTO RATEIO | F34: ATIVO | I34: regiao371@gmail.com | J34: 67992637973 | K34: TRIFÁSICO | L34: 0.25 | M34: 371 | O34: MS | P34: RUA GUANABARA, 146 - 17.047.05.488000 TELEMETRIA - 79240000 VILA ANGELICA I JARDIM (AG: 47) | Q34: 796.66667 | R34: 796.66667 | S34: =COUNTIFS(Faturamento!B:B,Base_Clientes[[#This Row],[INSTALAÇÃO]],Faturamento!V:V,"Atrasado") -> 0
A35: 10/218777-1 | B35: IGREJA DO EVANGELHO QUADRANGULAR | C35: 62.955.505/0170-51 | D35: ENERGISA MS | E35: APTO RATEIO | F35: ATIVO | I35: auxiliar.cedms@gmail.com | J35: 67999031330 | K35: BIFÁSICO | L35: 0.25 | M35: 306 | O35: MS | P35: RUA AMAZONAS 171 11.053.01.501000 - CENTRO CEP 79170000 - SIDROLANDIA / MS | Q35: 153.91667 | R35: 153.91667 | S35: =COUNTIFS(Faturamento!B:B,Base_Clientes[[#This Row],[INSTALAÇÃO]],Faturamento!V:V,"Atrasado") -> 0
A36: 10/226667-4 | B36: IGREJA DO EVANGELHO QUADRANGULAR | C36: 62.955.505/0408-94 | D36: ENERGISA MS | E36: APTO RATEIO | F36: ATIVO | I36: regiao371@gmail.com | J36: 67992637973 | K36: BIFÁSICO | L36: 0.25 | M36: 371 | O36: MS | P36: VISCONDE DE TAUNAY, 2925 CASA 1 X - CEP:79260000 - CENTRO - BELA VISTA MS | Q36: 157.66667 | R36: 157.66667 | S36: =COUNTIFS(Faturamento!B:B,Base_Clientes[[#This Row],[INSTALAÇÃO]],Faturamento!V:V,"Atrasado") -> 0
A37: 10/237441-1 | B37: IGREJA DO EVANGELHO QUADRANGULAR | C37: 62.955.505/0172-13 | D37: ENERGISA MS | E37: APTO RATEIO | F37: ATIVO | I37: regiao371@gmail.com | J37: 67992637973 | K37: TRIFÁSICO | L37: 0.25 | M37: 371 | O37: MS | P37: AVENIDA HERON DO COUTO S/N 14.061.05.032000 - MARAMBA CEP 79290000 - BONITO / MS | Q37: 166.66667 | R37: 166.66667 | S37: =COUNTIFS(Faturamento!B:B,Base_Clientes[[#This Row],[INSTALAÇÃO]],Faturamento!V:V,"Atrasado") -> 0
A38: 10/239312-2 | B38: IGREJA DO EVANGELHO QUADRANGULAR | C38: 62.955.505/0165-94 | D38: ENERGISA MS | E38: APTO RATEIO | F38: ATIVO | I38: ieqnioaque@gmail.com | J38: 67996711972 | K38: BIFÁSICO | L38: 0.25 | M38: 302 | O38: MS | P38: RUA TREZE DE MAIO 692 CENTRO CEP 79220000 - NIOAQUE / MS | Q38: 263.41667 | R38: 287.36364 | S38: =COUNTIFS(Faturamento!B:B,Base_Clientes[[#This Row],[INSTALAÇÃO]],Faturamento!V:V,"Atrasado") -> 0
A39: 10/24514-2 | B39: IGREJA DO EVANGELHO QUADRANGULAR | C39: 62.955.505/1570-66 | D39: ENERGISA MS | E39: APTO RATEIO | F39: ATIVO | I39: regiao.357.25@gmail.com | J39: 67996266684 | K39: TRIFÁSICO | L39: 0.25 | M39: 357 | O39: MS | P39: RUA SAO PAULO 36 CRISTO REDENTOR CEP 79311040 - CORUMBA / MS | Q39: 297.66667 | R39: 324.72727 | S39: =COUNTIFS(Faturamento!B:B,Base_Clientes[[#This Row],[INSTALAÇÃO]],Faturamento!V:V,"Atrasado") -> 1
A40: 10/252817-2 | B40: IGREJA DO EVANGELHO QUADRANGULAR | C40: 62.955.505/2740-20 | D40: ENERGISA MS | E40: APTO RATEIO | F40: ATIVO | I40: regiao371@gmail.com | J40: 67992637973 | K40: TRIFÁSICO | L40: 0.25 | M40: 371 | O40: MS | P40: RUA JOAO MARTINS LEITE 200 CENTRO CEP 79270000 - CARACOL / MS | Q40: 352.83333 | R40: 384.90909 | S40: =COUNTIFS(Faturamento!B:B,Base_Clientes[[#This Row],[INSTALAÇÃO]],Faturamento!V:V,"Atrasado") -> 0
A41: 10/257864-9 | B41: IGREJA DO EVANGELHO QUADRANGULAR | C41: 62.955.505/1821-76 | D41: ENERGISA MS | E41: ACOMPANHAR CRÉDITO | F41: ATIVO | G41: Inadimplência | H41: 45954 | J41: 67981311823 | K41: BIFÁSICO | L41: 0.25 | M41: 362 | O41: MS | P41: RUA SEN TEOTONIO VILELA 427 11.074.05.148000 - CENTRO, CEP 79965000 - ITAQUIRAI / MS | Q41: 153.91667 | R41: 153.91667 | S41: =COUNTIFS(Faturamento!B:B,Base_Clientes[[#This Row],[INSTALAÇÃO]],Faturamento!V:V,"Atrasado") -> 9
A42: 10/2599101-9 | B42: IGREJA DO EVANGELHO QUADRANGULAR | C42: 62.955.505/3793-95 | D42: ENERGISA MS | E42: APTO RATEIO | F42: ATIVO | I42: auxiliar.cedms@gmail.com | J42: 67991120875 | K42: TRIFÁSICO | L42: 0.25 | M42: 306 | O42: MS | P42: AVENIDA BANDEIRANTES, 0 - 79006001 GUANANDI CAMPO GRANDE (AG: 103) | Q42: 818 | R42: 818 | S42: =COUNTIFS(Faturamento!B:B,Base_Clientes[[#This Row],[INSTALAÇÃO]],Faturamento!V:V,"Atrasado") -> 1
A43: 10/2605731-5 | B43: IGREJA DO EVANGELHO QUADRANGULAR | C43: 62.955.505/0172-13 | D43: ENERGISA MS | E43: APTO RATEIO | F43: ATIVO | I43: regiao371@gmail.com | J43: 67992637973 | K43: TRIFÁSICO | L43: 0.25 | M43: 371 | O43: MS | P43: RUA LUIZ DA COSTA LEITE, 2177 - BONITO MS | Q43: 1056.1667 | R43: 1056.1667 | S43: =COUNTIFS(Faturamento!B:B,Base_Clientes[[#This Row],[INSTALAÇÃO]],Faturamento!V:V,"Atrasado") -> 0
A44: 10/260761-2 | B44: IGREJA DO EVANGELHO QUADRANGULAR | C44: 62.955.505/0001-67 | D44: ENERGISA MS | E44: APTO RATEIO | F44: ATIVO | I44: mariza.ieq@gmail.com | J44: 67996150274 | K44: TRIFÁSICO | L44: 0.25 | M44: 360 | O44: MS | P44: RUA PARANA, 2051 - 14.075.07.245000 - 79490000 - CENTRO - SÃO GABRIEL DO OESTE | Q44: 378.91667 | R44: 413.36364 | S44: =COUNTIFS(Faturamento!B:B,Base_Clientes[[#This Row],[INSTALAÇÃO]],Faturamento!V:V,"Atrasado") -> 0
A45: 10/276283-9 | B45: IGREJA DO EVANGELHO QUADRANGULAR | C45: 62.955.505/0884-04 | D45: ENERGISA MS | E45: APTO RATEIO | F45: ATIVO | I45: ieqcelsapucaia@gmail.com | J45: 46 999066691 | K45: TRIFÁSICO | L45: 0.25 | M45: 994 | O45: MS | P45: RUA ADOLFO DO AMARAL 284 15.085.81.377000 - JARDIM MONTIVIDEU, CEP 79995000 - CORONEL SAPUCAIA / MS | Q45: 335.75 | R45: 335.75 | S45: =COUNTIFS(Faturamento!B:B,Base_Clientes[[#This Row],[INSTALAÇÃO]],Faturamento!V:V,"Atrasado") -> 0
A46: 10/2794432-1 | B46: IGREJA DO EVANGELHO QUADRANGULAR | C46: 62.955.505/0151-99 | D46: ENERGISA MS | E46: APTO RATEIO | F46: ATIVO | I46: auxiliar.cedms@gmail.com | J46: 67991162146 | K46: TRIFÁSICO | L46: 0.25 | M46: 306 | O46: MS | P46: RUA BIRI, 503 - JARDIM CANGURU - CAMPO GRANDE/MS | Q46: 286.5 | R46: 286.5 | S46: =COUNTIFS(Faturamento!B:B,Base_Clientes[[#This Row],[INSTALAÇÃO]],Faturamento!V:V,"Atrasado") -> 0
A47: 10/280638-8 | B47: IGREJA DO EVANGELHO QUADRANGULAR | C47: 62.955.505/8432-53 | D47: ENERGISA MS | E47: APTO RATEIO | F47: ATIVO | I47: ieqreg349cassi@gmail.com | J47: 67 81355403 | K47: TRIFÁSICO | L47: 0.25 | M47: 349 | O47: MS | P47: RUA CARACOL 1292 CENTRO CEP 79560000 - CHAPADAO DO SUL / MS | Q47: 266 | R47: 290.18182 | S47: =COUNTIFS(Faturamento!B:B,Base_Clientes[[#This Row],[INSTALAÇÃO]],Faturamento!V:V,"Atrasado") -> 0
A48: 10/283183-2 | B48: IGREJA DO EVANGELHO QUADRANGULAR | C48: 62.955.505/2876-01 | D48: ENERGISA MS | E48: APTO RATEIO | F48: ATIVO | I48: renildofernandeslima@gmail.com | J48: 16 988508102 | K48: TRIFÁSICO | L48: 0.25 | M48: 994 | O48: MS | P48: AVENIDA ALBERTO RATIER 1200 CENTRO CEP 79925000 - PARANHOS / MS | Q48: 131.66667 | R48: 143.63636 | S48: =COUNTIFS(Faturamento!B:B,Base_Clientes[[#This Row],[INSTALAÇÃO]],Faturamento!V:V,"Atrasado") -> 0
A49: 10/29964-4 | B49: IGREJA DO EVANGELHO QUADRANGULAR | C49: 62.955.505/0676-60 | D49: ENERGISA MS | E49: APTO RATEIO | F49: ATIVO | I49: regiao.357.25@gmail.com | J49: 67996266684 | K49: TRIFÁSICO | L49: 0.25 | M49: 357 | O49: MS | P49: RUA PARANA, 2481, POPULAR NOVA, CORUMBA-MS | Q49: 708 | R49: 708 | S49: =COUNTIFS(Faturamento!B:B,Base_Clientes[[#This Row],[INSTALAÇÃO]],Faturamento!V:V,"Atrasado") -> 0
A50: 10/3030784-7 | B50: IGREJA DO EVANGELHO QUADRANGULAR | C50: 62.955.505/0160-80 | D50: ENERGISA MS | E50: APTO RATEIO | F50: ATIVO | I50: regiao.357.25@gmail.com | J50: 67996266684 | K50: TRIFÁSICO | L50: 0.25 | M50: 357 | O50: MS | P50: RUA SALDANHA DA GAMA, 15, CENTRO, LADARIO-MS | Q50: 468.66667 | R50: 468.66667 | S50: =COUNTIFS(Faturamento!B:B,Base_Clientes[[#This Row],[INSTALAÇÃO]],Faturamento!V:V,"Atrasado") -> 0
A51: 10/3040565-8 | B51: IGREJA DO EVANGELHO QUADRANGULAR | C51: 62.955.505/0154-31 | D51: ENERGISA MS | E51: APTO RATEIO | F51: ATIVO | I51: auxiliar.cedms@gmail.com | J51: 67996135721 | K51: BIFÁSICO | L51: 0.25 | M51: 319 | O51: MS | P51: RUA ANTONIO AMARO DE MATTOS 5413 07.010.34.501000 - VILA ROSA, CEP 79831130 - DOURADOS / MS | Q51: 229.41667 | R51: 250.27273 | S51: =COUNTIFS(Faturamento!B:B,Base_Clientes[[#This Row],[INSTALAÇÃO]],Faturamento!V:V,"Atrasado") -> 0
A52: 10/3054052-0 | B52: IGREJA DO EVANGELHO QUADRANGULAR | C52: 62.955.505/3124-87 | D52: ENERGISA MS | E52: APTO RATEIO | F52: ATIVO | I52: regiao.357.25@gmail.com | J52: 67996266684 | K52: TRIFÁSICO | L52: 0.25 | M52: 357 | O52: MS | P52: RUA FREI LIBERATO QUETTERE S/N NOVA ALIANCA CEP 79370000 - LADARIO / MS | Q52: 162.18182 | R52: 178.4 | S52: =COUNTIFS(Faturamento!B:B,Base_Clientes[[#This Row],[INSTALAÇÃO]],Faturamento!V:V,"Atrasado") -> 0
A53: 10/3092868-3 | B53: IGREJA DO EVANGELHO QUADRANGULAR | C53: 62.955.505/4194-43 | D53: ENERGISA MS | E53: APTO RATEIO | F53: ATIVO | I53: scr_prmarcal@hotmail.com | J53: 67 9967-7090 | K53: TRIFÁSICO | L53: 0.25 | M53: 331 | O53: MS | P53: RUA ELMODAM OLIVEIRA SOARES 1909, NOVA PORTO XV-MS | Q53: 433.16667 | R53: 433.16667 | S53: =COUNTIFS(Faturamento!B:B,Base_Clientes[[#This Row],[INSTALAÇÃO]],Faturamento!V:V,"Atrasado") -> 0
A54: 10/3123706-8 | B54: IGREJA DO EVANGELHO QUADRANGULAR | C54: 62.955.505/3757-21 | D54: ENERGISA MS | E54: ACOMPANHAR CRÉDITO | F54: ATIVO | G54: Inadimplência | H54: 45954 | I54: sergio_ieq@outlook.com | J54: 67999050448 | K54: TRIFÁSICO | L54: 0.25 | M54: 362 | O54: MS | P54: RUA CUIABA 225 CENTRO CEP 79950000 - NAVIRAI / MS | Q54: 335.41667 | R54: 365.90909 | S54: =COUNTIFS(Faturamento!B:B,Base_Clientes[[#This Row],[INSTALAÇÃO]],Faturamento!V:V,"Atrasado") -> 2
A55: 10/3125732-2 | B55: IGREJA DO EVANGELHO QUADRANGULAR | C55: 62.955.505/0155-12 | D55: ENERGISA MS | E55: ACOMPANHAR CRÉDITO | F55: INATIVO | G55: Solicitação de distrato | I55: ieqaral@gmail.com | J55: 65999839279 | K55: BIFÁSICO | L55: 0.25 | M55: 358 | O55: MS | P55: RUA QUINZE DE NOVEMBRO 182 CENTRO CEP 79930000 - ARAL MOREIRA / MS | Q55: 150.66667 | R55: 164.36364 | S55: =COUNTIFS(Faturamento!B:B,Base_Clientes[[#This Row],[INSTALAÇÃO]],Faturamento!V:V,"Atrasado") -> 0
A56: 10/31292-6 | B56: IGREJA DO EVANGELHO QUADRANGULAR | C56: 62.955.505/0160-80 | D56: ENERGISA MS | E56: ACOMPANHAR CRÉDITO | F56: INATIVO | G56: Solicitação de distrato | I56: regiao.357.25@gmail.com | J56: 67996266684 | K56: BIFÁSICO | L56: 0.25 | M56: 357 | O56: MS | P56: RUA CASTRO ALVES 166 BOA ESPERANCA CEP 79370000 - LADARIO / MS | Q56: 365 | R56: 167.54545 | S56: =COUNTIFS(Faturamento!B:B,Base_Clientes[[#This Row],[INSTALAÇÃO]],Faturamento!V:V,"Atrasado") -> 0
A57: 10/3139326-7 | B57: IGREJA DO EVANGELHO QUADRANGULAR | C57: 62.955.505/1822-57 | D57: ENERGISA MS | E57: APTO RATEIO | F57: ATIVO | I57: auxiliar.cedms@gmail.com | J57: 67999361728 | K57: TRIFÁSICO | L57: 0.25 | M57: 319 | O57: MS | P57: RUA ALBERTINA DE MATTOS S/N VILA SAO FRANCISCO CEP 79833280 - DOURADOS / MS | Q57: 460.25 | R57: 502.09091 | S57: =COUNTIFS(Faturamento!B:B,Base_Clientes[[#This Row],[INSTALAÇÃO]],Faturamento!V:V,"Atrasado") -> 0
A58: 10/341308-5 | B58: IGREJA DO EVANGELHO QUADRANGULAR | C58: 62.955.505/2391-19 | D58: ENERGISA MS | E58: APTO RATEIO | F58: ATIVO | I58: auxiliar.cedms@gmail.com | J58: 67993249456 | K58: BIFÁSICO | L58: 0.25 | M58: 306 | O58: MS | P58: RUA MAGNUS FONTAINE 121 VILA ALBUQUERQUE CEP 79060170 - CAMPO GRANDE / MS | Q58: 302.75 | R58: 330.27273 | S58: =COUNTIFS(Faturamento!B:B,Base_Clientes[[#This Row],[INSTALAÇÃO]],Faturamento!V:V,"Atrasado") -> 0
A59: 10/364440-8 | B59: IGREJA DO EVANGELHO QUADRANGULAR | C59: 62.955.505/0151-99 | D59: ENERGISA MS | E59: ACOMPANHAR CRÉDITO | F59: ATIVO | G59: Inadimplência | H59: 45954 | I59: auxiliar.cedms@gmail.com | J59: 67991120875 | K59: TRIFÁSICO | L59: 0.25 | M59: 306 | O59: MS | P59: AVENIDA BANDEIRANTES, 1437, GUANANDI, CAMPO GRANDE-MS | Q59: 2675.7508 | R59: 2675.7508 | S59: =COUNTIFS(Faturamento!B:B,Base_Clientes[[#This Row],[INSTALAÇÃO]],Faturamento!V:V,"Atrasado") -> 2
A60: 10/384823-1 | B60: IGREJA DO EVANGELHO QUADRANGULAR | C60: 62.955.505/0001-67 | D60: ENERGISA MS | E60: APTO RATEIO | F60: ATIVO | I60: prhelcio51@gmail.com | J60: 67999159477 | K60: MONOFÁSICO | L60: 0.25 | M60: 306 | O60: MS | P60: AVENIDA GEN ALBERTO CARLOS MENDONCA LIMA 2385 09.103.27.350000 - JARDIM SÃO CONRADO, CEP 79093290 - CAMPO GRANDE / MS | Q60: 144 | R60: 144 | S60: =COUNTIFS(Faturamento!B:B,Base_Clientes[[#This Row],[INSTALAÇÃO]],Faturamento!V:V,"Atrasado") -> 0
A61: 10/395471-6 | B61: IGREJA DO EVANGELHO QUADRANGULAR | C61: 62.955.505/2488-86 | D61: ENERGISA MS | E61: APTO RATEIO | F61: ATIVO | I61: sanderortigosa1@gmail.com | J61: 67992876000 | K61: TRIFÁSICO | L61: 0.25 | M61: 306 | O61: MS | P61: RUA VERDE LOURO 931 JARDIM TARUMA CEP 79097200 - CAMPO GRANDE / MS | Q61: 229 | R61: 249.81818 | S61: =COUNTIFS(Faturamento!B:B,Base_Clientes[[#This Row],[INSTALAÇÃO]],Faturamento!V:V,"Atrasado") -> 0
A62: 10/399338-3 | B62: IGREJA DO EVANGELHO QUADRANGULAR | C62: 62.955.505/2132-33 | D62: ENERGISA MS | E62: APTO RATEIO | F62: ATIVO | I62: auxiliar.cedms@gmail.com | J62: 67991060202 | K62: TRIFÁSICO | L62: 0.25 | M62: 306 | O62: MS | P62: RUA GENERAL ALCOFORADO 499 VILA PIRATININGA CEP 79081160 - CAMPO GRANDE / MS | Q62: 604.16667 | R62: 659.09091 | S62: =COUNTIFS(Faturamento!B:B,Base_Clientes[[#This Row],[INSTALAÇÃO]],Faturamento!V:V,"Atrasado") -> 0
A63: 10/40190-1 | B63: IGREJA DO EVANGELHO QUADRANGULAR | C63: 62.955.505/1775-04 | D63: ENERGISA MS | E63: ACOMPANHAR CRÉDITO | F63: INATIVO | G63: Solicitação de distrato | I63: auxiliar.cedms@gmail.com | J63: 67996859014 | K63: BIFÁSICO | L63: 0.25 | M63: 319 | O63: MS | P63: RUA JOSE VALERIO DOS SANTOS 435 PARQUE DAS NACOES II CEP 79842080 - DOURADOS / MS | Q63: 308.33333 | R63: 336.36364 | S63: =COUNTIFS(Faturamento!B:B,Base_Clientes[[#This Row],[INSTALAÇÃO]],Faturamento!V:V,"Atrasado") -> 4
A64: 10/41548-9 | B64: IGREJA DO EVANGELHO QUADRANGULAR | C64: 62.955.505/2690-26 | D64: ENERGISA MS | E64: ACOMPANHAR CRÉDITO | F64: INATIVO | G64: Solicitação de distrato | I64: auxiliar.cedms@gmail.com | J64: 67996687077 | K64: BIFÁSICO | L64: 0.25 | M64: 319 | O64: MS | P64: RUA JOAO VICENTE FERREIRA 6715 JARDIM MARACANA CEP 79833085 - DOURADOS / MS | Q64: 268.58333 | R64: 293 | S64: =COUNTIFS(Faturamento!B:B,Base_Clientes[[#This Row],[INSTALAÇÃO]],Faturamento!V:V,"Atrasado") -> 0
A65: 10/435964-2 | B65: IGREJA DO EVANGELHO QUADRANGULAR | C65: 62.955.505/3574-05 | D65: ENERGISA MS | E65: APTO RATEIO | F65: ATIVO | I65: auxiliar.cedms@gmail.com | J65: 67992021114 | K65: TRIFÁSICO | L65: 0.25 | M65: 306 | O65: MS | P65: RUA THEODORO ROOSEVELT 1263 VILA MARLI CEP 79116191 - CAMPO GRANDE / MS | Q65: 346.58333 | R65: 378.09091 | S65: =COUNTIFS(Faturamento!B:B,Base_Clientes[[#This Row],[INSTALAÇÃO]],Faturamento!V:V,"Atrasado") -> 0
A66: 10/452884-0 | B66: IGREJA DO EVANGELHO QUADRANGULAR | C66: 62.955.505/0001-67 | D66: ENERGISA MS | E66: APTO RATEIO | F66: ATIVO | I66: israelregiao302@gmail.com | J66: 67 996469842 | K66: BIFÁSICO | L66: 0.25 | M66: 302 | O66: MS | P66: AVENIDA CAMISAO S/N 06.201.90.426000 - CAMISAO CEP 79202000 - CAMISAO / MS | Q66: 147.33333 | R66: 147.33333 | S66: =COUNTIFS(Faturamento!B:B,Base_Clientes[[#This Row],[INSTALAÇÃO]],Faturamento!V:V,"Atrasado") -> 0
A67: 10/466560-0 | B67: IGREJA DO EVANGELHO QUADRANGULAR | C67: 62.955.505/0155-12 | D67: ENERGISA MS | E67: APTO RATEIO | F67: ATIVO | I67: rochachimenezhilda@gmail.com | J67: 67998302932 | K67: BIFÁSICO | L67: 0.25 | M67: 358 | O67: MS | P67: RUA MARCILIANO MACIEL 246 SANGA PUITA CEP 79900000 - SANGA PUITA / MS | Q67: 163.16667 | R67: 178 | S67: =COUNTIFS(Faturamento!B:B,Base_Clientes[[#This Row],[INSTALAÇÃO]],Faturamento!V:V,"Atrasado") -> 0
A68: 10/480529-7 | B68: IGREJA DO EVANGELHO QUADRANGULAR | C68: 62.955.505/1822-57 | D68: ENERGISA MS | E68: APTO RATEIO | F68: ATIVO | I68: auxiliar.cedms@gmail.com | J68: 6796411024 | K68: TRIFÁSICO | L68: 0.25 | M68: 319 | O68: MS | P68: RUA EULALIA PIRES 240 VILA CACHOEIRINHA CEP 79814330 - DOURADOS / MS | Q68: 331.66667 | R68: 361.81818 | S68: =COUNTIFS(Faturamento!B:B,Base_Clientes[[#This Row],[INSTALAÇÃO]],Faturamento!V:V,"Atrasado") -> 0
A69: 10/489076-0 | B69: IGREJA DO EVANGELHO QUADRANGULAR | C69: 62.955.505/0160-80 | D69: ENERGISA MS | E69: APTO RATEIO | F69: ATIVO | I69: regiao.357.25@gmail.com | J69: 67996266684 | K69: TRIFÁSICO | L69: 0.25 | M69: 357 | O69: MS | P69: RUA MARCILIO DIAS 939 CENTRO CEP 79370000 - LADARIO / MS | Q69: 467.91667 | R69: 510.45455 | S69: =COUNTIFS(Faturamento!B:B,Base_Clientes[[#This Row],[INSTALAÇÃO]],Faturamento!V:V,"Atrasado") -> 1
A70: 10/501586-2 | B70: IGREJA DO EVANGELHO QUADRANGULAR | C70: 62.955.505/2730-58 | D70: ENERGISA MS | E70: APTO RATEIO | F70: ATIVO | I70: auxiliar.cedms@gmail.com | J70: 67 92480766 | K70: TRIFÁSICO | L70: 0.25 | M70: 306 | O70: MS | P70: RUA LEONIDAS DE MATOS 841 05.104.11.174000 - SANTO ANTONIO, CEP 79100300 - CAMPO GRANDE / MS | Q70: 187.5 | R70: 187.5 | S70: =COUNTIFS(Faturamento!B:B,Base_Clientes[[#This Row],[INSTALAÇÃO]],Faturamento!V:V,"Atrasado") -> 0
A71: 10/504844-2 | B71: IGREJA DO EVANGELHO QUADRANGULAR | C71: 62.955.505/3544-81 | D71: ENERGISA MS | E71: APTO RATEIO | F71: ATIVO | I71: regiao371@gmail.com | J71: 67992637973 | K71: TRIFÁSICO | L71: 0.25 | M71: 371 | O71: MS | P71: AVENIDA DO AEROPORTO S/N CENTRO CEP 79390000 - BODOQUENA / MS | Q71: 397.41667 | R71: 433.54545 | S71: =COUNTIFS(Faturamento!B:B,Base_Clientes[[#This Row],[INSTALAÇÃO]],Faturamento!V:V,"Atrasado") -> 0
A72: 10/505854-0 | B72: IGREJA DO EVANGELHO QUADRANGULAR | C72: 62.955.505/8873-82 | D72: ENERGISA MS | E72: APTO RATEIO | F72: ATIVO | I72: regiao351@gmail.com | J72: 67996446178 | K72: TRIFÁSICO | L72: 0.25 | M72: 351 | O72: MS | P72: AVENIDA PRESIDENTE DUTRA 925 CENTRO CEP 79880000 - DOURADINA / MS | Q72: 432.33333 | R72: 93.7 | S72: =COUNTIFS(Faturamento!B:B,Base_Clientes[[#This Row],[INSTALAÇÃO]],Faturamento!V:V,"Atrasado") -> 0
A73: 10/510330-4 | B73: IGREJA DO EVANGELHO QUADRANGULAR | C73: 62.955.505/3671-17 | D73: ENERGISA MS | E73: APTO RATEIO | F73: ATIVO | I73: adalberto123franca@gmail.com | J73: 67992637973 | K73: TRIFÁSICO | L73: 0.25 | M73: 358 | O73: MS | P73: TRAVESSA JOSE MAURO OCAMPOS, 498, PORTAL DO MORUMBI, PONTA PORÃ | Q73: 586 | R73: 586 | S73: =COUNTIFS(Faturamento!B:B,Base_Clientes[[#This Row],[INSTALAÇÃO]],Faturamento!V:V,"Atrasado") -> 0
A74: 10/511753-6 | B74: IGREJA DO EVANGELHO QUADRANGULAR | C74: 62.955.505/0160-80 | D74: ENERGISA MS | E74: APTO RATEIO | F74: ATIVO | I74: regiao.357.25@gmail.com | J74: 67996266684 | K74: BIFÁSICO | L74: 0.25 | M74: 357 | O74: MS | P74: RUA PEDRO FELICIDADE 351 04.004.01.200077 - CENTRO CEP 79370000 - LADARIO | Q74: 215.58333 | R74: 215.58333 | S74: =COUNTIFS(Faturamento!B:B,Base_Clientes[[#This Row],[INSTALAÇÃO]],Faturamento!V:V,"Atrasado") -> 0
A75: 10/512142-1 | B75: IGREJA DO EVANGELHO QUADRANGULAR | C75: 62.955.505/1893-40 | D75: ENERGISA MS | E75: ACOMPANHAR CRÉDITO | F75: INATIVO | G75: Solicitação de distrato | I75: ieqreg349cassi@gmail.com | J75: 67 81355403 | K75: TRIFÁSICO | L75: 0.25 | M75: 349 | O75: MS | P75: RUA OLINDA MARIA DE MENEZES 1968 JARDIM SAO VICENTE CEP 79570000 - APARECIDA DO TABOADO / MS | Q75: 232.91667 | R75: 254.09091 | S75: =COUNTIFS(Faturamento!B:B,Base_Clientes[[#This Row],[INSTALAÇÃO]],Faturamento!V:V,"Atrasado") -> 0
A76: 10/513413-5 | B76: IGREJA DO EVANGELHO QUADRANGULAR | C76: 62.955.505/3216-30 | D76: ENERGISA MS | E76: ACOMPANHAR CRÉDITO | F76: INATIVO | G76: Solicitação de distrato | I76: regiao371@gmail.com | J76: 67992637973 | K76: TRIFÁSICO | L76: 0.25 | M76: 371 | O76: MS | P76: RUA TREZE DE MAIO, 1200, VILA SÃO MIGUEL, GUIA LOPES DA LAGUNA | Q76: 513.41667 | R76: 513.41667 | S76: =COUNTIFS(Faturamento!B:B,Base_Clientes[[#This Row],[INSTALAÇÃO]],Faturamento!V:V,"Atrasado") -> 0
A77: 10/5202-7 | B77: IGREJA DO EVANGELHO QUADRANGULAR | C77: 62.955.505/0161-60 | D77: ENERGISA MS | E77: APTO RATEIO | F77: ATIVO | I77: israelregiao302@gmail.com | J77: 67 996469842 | K77: TRIFÁSICO | L77: 0.25 | M77: 302 | O77: MS | P77: RUA DUQUE DE CAXIAS, 887, CENTRO, AQUIDAUANA-MS | Q77: 1810.6008 | R77: 1810.6008 | S77: =COUNTIFS(Faturamento!B:B,Base_Clientes[[#This Row],[INSTALAÇÃO]],Faturamento!V:V,"Atrasado") -> 0
A78: 10/52987-5 | B78: IGREJA DO EVANGELHO QUADRANGULAR | C78: 62.955.505/1822-57 | D78: ENERGISA MS | E78: APTO RATEIO | F78: ATIVO | I78: auxiliar.cedms@gmail.com | J78: 67996983476 | K78: TRIFÁSICO | L78: 0.25 | M78: 319 | O78: MS | P78: RUA SALVIANO PEDROSO 1150 JARDIM AGUA BOA CEP 79812170 - DOURADOS / MS | Q78: 242 | R78: 264 | S78: =COUNTIFS(Faturamento!B:B,Base_Clientes[[#This Row],[INSTALAÇÃO]],Faturamento!V:V,"Atrasado") -> 0
A79: 10/530195-7 | B79: IGREJA DO EVANGELHO QUADRANGULAR | C79: 62.955.505/3671-17 | D79: ENERGISA MS | E79: APTO RATEIO | F79: ATIVO | I79: pastoreliasmn@hotmail.com | J79: 67999516782 | K79: BIFÁSICO | L79: 0.25 | M79: 362 | O79: MS | P79: RUA JONAS PEDRO NUNES 1576 CENTRO CEP 79760000 - BATAYPORA / MS | Q79: 112.25 | R79: 122.45455 | S79: =COUNTIFS(Faturamento!B:B,Base_Clientes[[#This Row],[INSTALAÇÃO]],Faturamento!V:V,"Atrasado") -> 0
A80: 10/532081-7 | B80: IGREJA DO EVANGELHO QUADRANGULAR | C80: 62.955.505/1935-34 | D80: ENERGISA MS | E80: APTO RATEIO | F80: ATIVO | I80: eugeniorodrigues2020@gmail.com; quadrangular994@gmail.com | J80: 67 992321318 | K80: TRIFÁSICO | L80: 0.25 | M80: 994 | O80: MS | P80: RUA CASSIANO MARCELO 923 CENTRO CEP 79990000 - AMAMBAI / MS | Q80: 350.91667 | R80: 350.91667 | S80: =COUNTIFS(Faturamento!B:B,Base_Clientes[[#This Row],[INSTALAÇÃO]],Faturamento!V:V,"Atrasado") -> 1
A81: 10/532723-4 | B81: IGREJA DO EVANGELHO QUADRANGULAR | C81: 62.955.505/3593-60 | D81: ENERGISA MS | E81: ACOMPANHAR CRÉDITO | F81: ATIVO | G81: Inadimplência | H81: 45954 | I81: regiao351@gmail.com | J81: 67996446178 | K81: TRIFÁSICO | L81: 0.25 | M81: 351 | O81: MS | P81: RUA DUAIR JOAO DE BARCELOS 267 CENTRO CEP 79140000 - NOVA ALVORADA DO SUL / MS | Q81: 409.33333 | R81: 409.33333 | S81: =COUNTIFS(Faturamento!B:B,Base_Clientes[[#This Row],[INSTALAÇÃO]],Faturamento!V:V,"Atrasado") -> 4
A82: 10/61344-8 | B82: IGREJA DO EVANGELHO QUADRANGULAR | C82: 62.955.505/0154-31 | D82: ENERGISA MS | E82: APTO RATEIO | F82: ATIVO | I82: auxiliar.cedms@gmail.com | J82: 67999998719 | K82: BIFÁSICO | L82: 0.25 | M82: 319 | O82: MS | P82: RUA CUIABA 3395 CENTRO CEP 79802031 - DOURADOS / MS | Q82: 739.58333 | R82: 806.81818 | S82: =COUNTIFS(Faturamento!B:B,Base_Clientes[[#This Row],[INSTALAÇÃO]],Faturamento!V:V,"Atrasado") -> 1
A83: 10/63920-3 | B83: IGREJA DO EVANGELHO QUADRANGULAR | C83: 62.955.505/1355-00 | D83: ENERGISA MS | E83: APTO RATEIO | F83: ATIVO | I83: auxiliar.cedms@gmail.com | J83: 67981263396 | K83: TRIFÁSICO | L83: 0.25 | M83: 319 | O83: MS | P83: RUA INOCENCIA DE MATOS OSORIO 240 JARDIM MATO GROSSO CEP 79814040 - DOURADOS / MS | Q83: 353.5 | R83: 385.63636 | S83: =COUNTIFS(Faturamento!B:B,Base_Clientes[[#This Row],[INSTALAÇÃO]],Faturamento!V:V,"Atrasado") -> 0
A84: 10/69319-2 | B84: IGREJA DO EVANGELHO QUADRANGULAR | C84: 62.955.505/1822-57 | D84: ENERGISA MS | E84: APTO RATEIO | F84: ATIVO | I84: auxiliar.cedms@gmail.com | J84: 67998363594 | K84: TRIFÁSICO | L84: 0.25 | M84: 319 | O84: MS | P84: RUA ANTONIO ALVES ROCHA 635 PANAMBI VERA CEP 79822200 - DOURADOS / MS | Q84: 32.666667 | R84: 392 | S84: =COUNTIFS(Faturamento!B:B,Base_Clientes[[#This Row],[INSTALAÇÃO]],Faturamento!V:V,"Atrasado") -> 0
A85: 10/72605-9 | B85: IGREJA DO EVANGELHO QUADRANGULAR | C85: 62.955.505/1364-92 | D85: ENERGISA MS | E85: APTO RATEIO | F85: ATIVO | I85: auxiliar.cedms@gmail.com | J85: 67996071169 | K85: TRIFÁSICO | L85: 0.25 | M85: 319 | O85: MS | P85: AVENIDA MARCELINO PIRES 287 JARDIM CLIMAX CEP 79820010 - DOURADOS / MS | Q85: 288.75 | R85: 315 | S85: =COUNTIFS(Faturamento!B:B,Base_Clientes[[#This Row],[INSTALAÇÃO]],Faturamento!V:V,"Atrasado") -> 0
A86: 10/76927-3 | B86: IGREJA DO EVANGELHO QUADRANGULAR | C86: 62.955.505/0585-99 | D86: ENERGISA MS | E86: APTO RATEIO | F86: ATIVO | I86: lucashenriquemarianorosa@gmail.com | J86: 67 999373813 | K86: TRIFÁSICO | L86: 0.25 | M86: 302 | O86: MS | P86: RUA EXPEDICIONARIO CANDIDO GOMES CENTRO CEP 79210000 - ANASTACIO / MS | Q86: 323.25 | R86: 352.63636 | S86: =COUNTIFS(Faturamento!B:B,Base_Clientes[[#This Row],[INSTALAÇÃO]],Faturamento!V:V,"Atrasado") -> 1
A87: 10/78338-1 | B87: IGREJA DO EVANGELHO QUADRANGULAR | C87: 62.955.505/0168-37 | D87: ENERGISA MS | E87: APTO RATEIO | F87: ATIVO | I87: maurolimaaquino@hotmail.com | J87: 67 984742936 | K87: TRIFÁSICO | L87: 0.25 | M87: 302 | O87: MS | P87: RUA 27 DE JULHO, 1200 CENTRO 79210000 CENTRO ANASTACIO / MS | Q87: 262.33333 | R87: 286.18182 | S87: =COUNTIFS(Faturamento!B:B,Base_Clientes[[#This Row],[INSTALAÇÃO]],Faturamento!V:V,"Atrasado") -> 0
A88: 10/81222-2 | B88: IGREJA DO EVANGELHO QUADRANGULAR | C88: 62.955.505/0159-46 | D88: ENERGISA MS | E88: APTO RATEIO | F88: ATIVO | I88: i.e.qmiranda302@gmail.com | J88: 67 992491551 | K88: TRIFÁSICO | L88: 0.25 | M88: 302 | O88: MS | P88: RUA BENJAMIN CONSTANT 923 CENTRO CEP 79380000 - MIRANDA / MS | Q88: 423 | R88: 461.45455 | S88: =COUNTIFS(Faturamento!B:B,Base_Clientes[[#This Row],[INSTALAÇÃO]],Faturamento!V:V,"Atrasado") -> 0
A89: 10/8777-5 | B89: IGREJA DO EVANGELHO QUADRANGULAR | C89: 62.955.505/1224-32 | D89: ENERGISA MS | E89: ACOMPANHAR CRÉDITO | F89: INATIVO | G89: Solicitação de distrato | I89: adriana.santos@sanesul.ms.gov.br | J89: 67 992319530 | K89: TRIFÁSICO | L89: 0.25 | M89: 302 | O89: MS | P89: RUA GIOVANI TOSCANO DE BRITO 2648 CENTRO CEP 79200000 - AQUIDAUANA / MS | Q89: 390.83333 | R89: 426.36364 | S89: =COUNTIFS(Faturamento!B:B,Base_Clientes[[#This Row],[INSTALAÇÃO]],Faturamento!V:V,"Atrasado") -> 0
A90: 10/908866-7 | B90: IGREJA DO EVANGELHO QUADRANGULAR | C90: 62.955.505/3586-30 | D90: ENERGISA MS | E90: APTO RATEIO | F90: ATIVO | I90: regiao371@gmail.com | J90: 67992637973 | K90: TRIFÁSICO | L90: 0.25 | M90: 371 | O90: MS | P90: RUA APARECIDO PEREIRA BUENO, 1273 - 01.047.17.111577 - 79240000 - VILA ANGELICA II - JARDIM | Q90: 161.25 | R90: 175.90909 | S90: =COUNTIFS(Faturamento!B:B,Base_Clientes[[#This Row],[INSTALAÇÃO]],Faturamento!V:V,"Atrasado") -> 0
A91: 10/931327-1 | B91: IGREJA DO EVANGELHO QUADRANGULAR | C91: 62.955.505/4027-10 | D91: ENERGISA MS | E91: APTO RATEIO | F91: ATIVO | I91: pastorsilviocesar@hotmail.com | J91: 17996297425 | K91: TRIFÁSICO | L91: 0.25 | M91: 994 | O91: MS | P91: RUA ALCINDO FRANCO MACHADO 951 10.036.25.249000 - VILA MARTINS CEP 79990000 - AMAMBAI / MS | Q91: 274.25 | R91: 274.25 | S91: =COUNTIFS(Faturamento!B:B,Base_Clientes[[#This Row],[INSTALAÇÃO]],Faturamento!V:V,"Atrasado") -> 0
A92: 10/952579-1 | B92: IGREJA DO EVANGELHO QUADRANGULAR | C92: 62.955.505/8979-30 | D92: ENERGISA MS | E92: APTO RATEIO | F92: ATIVO | I92: mariza.ieq@gmail.com | J92: 67996150274 | K92: BIFÁSICO | L92: 0.25 | M92: 360 | O92: MS | P92: RUA PRESIDENTE VARGAS 42 CENTRO CEP 79415000 - SONORA / MS | Q92: 148.83333 | R92: 162.36364 | S92: =COUNTIFS(Faturamento!B:B,Base_Clientes[[#This Row],[INSTALAÇÃO]],Faturamento!V:V,"Atrasado") -> 0
A93: 10/987178-1 | B93: IGREJA DO EVANGELHO QUADRANGULAR | C93: 62.955.505/0155-12 | D93: ENERGISA MS | E93: APTO RATEIO | F93: ATIVO | I93: lucianop.duarte@outlook.com | J93: 67993496482 | K93: TRIFÁSICO | L93: 0.25 | M93: 358 | O93: MS | P93: RUA JOAO PONCE DE ARRUDA 697 09.032.06.230000 - VILA VITORIA CEP 79906766 - PONTA PORA / MS | Q93: 123.5 | R93: 123.5 | S93: =COUNTIFS(Faturamento!B:B,Base_Clientes[[#This Row],[INSTALAÇÃO]],Faturamento!V:V,"Atrasado") -> 0
A94: 10/3556072-1 | B94: IGREJA DO EVANGELHO QUADRANGULAR | C94: 62.955.505/0164-03 | D94: ENERGISA MS | E94: APTO RATEIO | F94: ATIVO | I94: ieqdejardim@gmail.com | K94: BIFÁSICO | L94: 0.25 | O94: MS | P94: RUA CORUMBA, 39 - VILA ANGELICA - JARDIM CEP 7924000 | Q94: 226 | R94: 226 | S94: =COUNTIFS(Faturamento!B:B,Base_Clientes[[#This Row],[INSTALAÇÃO]],Faturamento!V:V,"Atrasado") -> 0
A95: 10/141631-2 | B95: IGREJA DO EVANGELHO QUADRANGULAR | C95: 62.955.505/0155-12 | D95: ENERGISA MS | E95: APTO RATEIO | F95: ATIVO | I95: regiao358ms@gmail.com | J95: 67 992337953 | K95: TRIFÁSICO | L95: 0.25 | M95: 358 | O95: MS | P95: RUA ALEXANDRE GUSMAO 268 06.032.02.052000 - CENTRO CEP 79904726 - PONTA PORA / MS | Q95: 180.02 | R95: 180.02 | S95: =COUNTIFS(Faturamento!B:B,Base_Clientes[[#This Row],[INSTALAÇÃO]],Faturamento!V:V,"Atrasado") -> 0
A96: 10/151994-1 | B96: IGREJA DO EVANGELHO QUADRANGULAR | C96: 62.955.505/0155-12 | D96: ENERGISA MS | E96: APTO RATEIO | F96: ATIVO | I96: regiao358ms@gmail.com | J96: 67 992337953 | K96: BIFÁSICO | L96: 0.25 | M96: 358 | O96: MS | P96: RUA LUIZ QUINTANA 107 01.032.25.605000 - FLAMBOYANT RESIDENCIAL PARK CEP 79906084 - PONTA PORA / MS | Q96: 254.93 | R96: 254.93 | S96: =COUNTIFS(Faturamento!B:B,Base_Clientes[[#This Row],[INSTALAÇÃO]],Faturamento!V:V,"Atrasado") -> 0

Sheet Inadimplência
A1: Status Pagamento | B1: (Vários itens)
A3: Mês Ref | B3: Qted | C3: Total Emitido (R$) | D3: Total Pago (R$) | E3: Valor em Acordo | F3: Valor Inadimplente | G3: % inadimplência
A4: 45658 | B4: 84 | C4: 19964.24 | D4: 19059.44 | E4: =SUMIFS(Faturamento!R:R,Faturamento!G:G,Inadimplência!A4,Faturamento!V:V,"Acordo") -> 0 | F4: =C4-D4-E4 -> 904.8 | G4: =F4/C4 -> 0.045321034
A5: 45689 | B5: 50 | C5: 16003.59 | D5: 15264.88 | E5: =SUMIFS(Faturamento!R:R,Faturamento!G:G,Inadimplência!A5,Faturamento!V:V,"Acordo") -> 0 | F5: =C5-D5-E5 -> 738.71 | G5: =F5/C5 -> 0.046159018
A6: 45717 | B6: 55 | C6: 17915 | D6: 17007.83 | E6: =SUMIFS(Faturamento!R:R,Faturamento!G:G,Inadimplência!A6,Faturamento!V:V,"Acordo") -> 0 | F6: =C6-D6-E6 -> 907.17 | G6: =F6/C6 -> 0.050637455
A7: 45748 | B7: 86 | C7: 18900.91 | D7: 16189.3 | E7: =SUMIFS(Faturamento!R:R,Faturamento!G:G,Inadimplência!A7,Faturamento!V:V,"Acordo") -> 175.21 | F7: =C7-D7-E7 -> 2536.4 | G7: =F7/C7 -> 0.1341946
A8: 45778 | B8: 83 | C8: 16645.9 | D8: 14193.639 | E8: =SUMIFS(Faturamento!R:R,Faturamento!G:G,Inadimplência!A8,Faturamento!V:V,"Acordo") -> 0 | F8: =C8-D8-E8 -> 2452.261 | G8: =F8/C8 -> 0.14731922
A9: 45809 | B9: 63 | C9: 9822.37 | D9: 9532.5733 | E9: =SUMIFS(Faturamento!R:R,Faturamento!G:G,Inadimplência!A9,Faturamento!V:V,"Acordo") -> 0 | F9: =C9-D9-E9 -> 289.79667 | G9: =F9/C9 -> 0.029503742
A10: 45839 | B10: 75 | C10: 12120.21 | D10: 12060.14 | E10: =SUMIFS(Faturamento!R:R,Faturamento!G:G,Inadimplência!A10,Faturamento!V:V,"Acordo") -> 161.56 | F10: =C10-D10-E10 -> -101.49 | G10: 0
A11: 45870 | B11: 78 | C11: 14372.97 | D11: 14030.1 | E11: =SUMIFS(Faturamento!R:R,Faturamento!G:G,Inadimplência!A11,Faturamento!V:V,"Acordo") -> 172.03 | F11: =C11-D11-E11 -> 170.84 | G11: =F11/C11 -> 0.0118862
A12: 45901 | B12: 79 | C12: 18122.97 | D12: 17328.501 | E12: =SUMIFS(Faturamento!R:R,Faturamento!G:G,Inadimplência!A12,Faturamento!V:V,"Acordo") -> 0 | F12: =C12-D12-E12 -> 794.46947 | G12: =F12/C12 -> 0.043837708
A13: 45931 | B13: 85 | C13: 23671.21 | D13: 22313.22 | E13: =SUMIFS(Faturamento!R:R,Faturamento!G:G,Inadimplência!A13,Faturamento!V:V,"Acordo") -> 0 | F13: =C13-D13-E13 -> 1357.99 | G13: =F13/C13 -> 0.057368846
A14: 45962 | B14: 87 | C14: 28544.62 | D14: 18614.41 | E14: =SUMIFS(Faturamento!R:R,Faturamento!G:G,Inadimplência!A14,Faturamento!V:V,"Acordo") -> 0 | F14: =C14-D14-E14 -> 9930.21 | G14: =F14/C14 -> 0.34788377
A15: Total Geral | B15: 825 | C15: 196083.99 | D15: 175594.03 | E15: =SUM(E4:E12) -> 508.8 | F15: =SUM(F4:F12) -> 8692.9571 | G15: =AVERAGE(G4:G12) -> 0.056539886
A17: Mês Ref | B17: % atual | C17: % anterior | D17: Redução
A18: 45658 | B18: 0.045321034 | C18: 0.045321034 | D18: =B18-C18 -> 0
A19: 45689 | B19: 0.046159018 | C19: 0.046159018 | D19: =B19-C19 -> 0
A20: 45717 | B20: 0.050637455 | C20: 0.050637455 | D20: =B20-C20 -> 0
A21: 45748 | B21: 0.13002646 | C21: 0.13883247 | D21: =B21-C21 -> -0.0088060106
A22: 45778 | B22: 0.16754162 | C22: 0.17203275 | D22: =B22-C22 -> -0.004491136
A23: 45809 | B23: 0.029503742 | C23: 0.035513832 | D23: =B23-C23 -> -0.0060100906
A24: 45839 | B24: 0 | C24: 0.005212781 | D24: =B24-C24 -> -0.005212781
A25: 45870 | B25: 0.01543244 | C25: 0.01543244 | D25: =B25-C25 -> -1.2490009e-16
A26: 45901 | B26: 0.043838 | C26: 0.065625005 | D26: =B26-C26 -> -0.021787005
A27: 45931 | B27: 0.139392 | C27: 0.14 | D27: =B27-C27 -> -0.000608
A29: Representatividade Inadimplencia por região
A31: Status Pagamento | B31: Atrasado
A33: Região | B33: % inadimplente
A34: Total Geral | B34: #DIV/0!

Sheet Processos
A1: Processos EGS: | B1: Gestão de Energia | C1: Atendimento
A2: 1. Rateio | B2: to do: tentar internalizar esse processo | C2: envio base para Livia dia 20
A3: 2. Alterações contratuais | B3: verificação da base antes de envio do rateio | C3: alteração direta na base
A4: 3. Acesso às faturas | B4: Thiago responsável | C4: Acompanhamento dos recebimentos
A5: 4. Entrada / Saída unidade | B5: verificação da base antes de envio do rateio | C5: indicar na base / Prazo até 90 para retirada total /cobrança de crédito acumulado
A6: 5. Faturamento | B6: Liberação relatório 1 dia útil antes do dia 10 | C6: Faturamento todo dia 10
A7: 6. Pagamento Inadimplência | B7: to do: Inclusão no relatório da coluna "Calculo HUBE final sem desconto" | C7: Realizar as cobranças com base no boleto sem desconto
A8: 7. Conciliação pagamento inadimplencia | B8: Utilizar a base de clientes - aba Faturamento | C8: utilizar extrato Ictus para atualização

Sheet Contatos - Ref.Jun-25
A1: CONTATO | B1: RAZÃO | C1: SOLUÇÃO | D1: RESPONSÁVEL UC | E1: RESPONSÁVEL REGIONAL | F1: 1- Reforçar se o e-mail de recebimento das faturas está correto e se recebeu a fatura enviada dia 21/07. 2- Informar o nosso e-mail de atendimento (atendimento@egsenergia.com.br), que é o mesmo que foi encaminhada a fatura Jun/25. 3- Comunicar que em breve disponibilizaremos o canal de WhatsApp (Executivo de Contas - Adriano)
A2: 67991120875 | B2: IGREJA DO EVANGELHO QUADRANGULAR | C2: EGS ENERGIA | E2: Adriana
A3: 67 996469842 | B3: IGREJA DO EVANGELHO QUADRANGULAR | C3: EGS ENERGIA | E3: Adriana
A4: 67992637973 | B4: IGREJA DO EVANGELHO QUADRANGULAR | C4: EGS ENERGIA | E4: Adriana
A5: 67996266684 | B5: IGREJA DO EVANGELHO QUADRANGULAR | C5: EGS ENERGIA | E5: Adriana
A6: 67 81355403 | B6: IGREJA DO EVANGELHO QUADRANGULAR | C6: EGS ENERGIA | E6: Adriana
A7: 67 992466753 | B7: IGREJA DO EVANGELHO QUADRANGULAR | C7: EGS ENERGIA | E7: Adriana
A8: 67 91285460 | B8: IGREJA DO EVANGELHO QUADRANGULAR | C8: EGS ENERGIA | E8: Adriana
A9: 46 999066691 | B9: IGREJA DO EVANGELHO QUADRANGULAR | C9: EGS ENERGIA | E9: Adriana
A10: 67996446178 | B10: IGREJA DO EVANGELHO QUADRANGULAR | C10: EGS ENERGIA | E10: Adriana
A11: 67996135721 | B11: IGREJA DO EVANGELHO QUADRANGULAR | C11: EGS ENERGIA | E11: Adriana
A12: 67 992321318 | B12: IGREJA DO EVANGELHO QUADRANGULAR | C12: EGS ENERGIA | E12: Adriana
A13: 67 998338301 | B13: IGREJA DO EVANGELHO QUADRANGULAR | C13: EGS ENERGIA | E13: Adriana
A14: 67991767866 | B14: IGREJA DO EVANGELHO QUADRANGULAR | C14: EGS ENERGIA | E14: Adriana
A15: 67 992158055 | B15: IGREJA DO EVANGELHO QUADRANGULAR | C15: EGS ENERGIA | E15: Adriana
A16: 67992337953 | B16: IGREJA DO EVANGELHO QUADRANGULAR | C16: EGS ENERGIA | E16: Adriana
A17: 67996575782 | B17: IGREJA DO EVANGELHO QUADRANGULAR | C17: EGS ENERGIA | E17: Adriana
A18: 67 96034976 | B18: IGREJA DO EVANGELHO QUADRANGULAR | C18: EGS ENERGIA | E18: Adriana
A19: 67999516782 | B19: IGREJA DO EVANGELHO QUADRANGULAR | C19: EGS ENERGIA | E19: Adriana
A20: 67 92480766 | B20: IGREJA DO EVANGELHO QUADRANGULAR | C20: EGS ENERGIA | E20: Adriana
A21: 67996150274 | B21: IGREJA DO EVANGELHO QUADRANGULAR | C21: EGS ENERGIA | E21: Adriana
A22: 67999031330 | B22: IGREJA DO EVANGELHO QUADRANGULAR | C22: EGS ENERGIA | E22: Adriana
A23: 67993496482 | B23: IGREJA DO EVANGELHO QUADRANGULAR | C23: EGS ENERGIA | E23: Adriana
A24: 67 996415566 | B24: IGREJA DO EVANGELHO QUADRANGULAR | C24: EGS ENERGIA | E24: Adriana
A25: 67999159477 | B25: IGREJA DO EVANGELHO QUADRANGULAR | C25: EGS ENERGIA | E25: Adriana
A26: 67991120875 | B26: IGREJA DO EVANGELHO QUADRANGULAR | C26: EGS ENERGIA | E26: Adriana
A27: 67991162146 | B27: IGREJA DO EVANGELHO QUADRANGULAR | C27: EGS ENERGIA | E27: Adriana
A28: 67 999373813 | B28: IGREJA DO EVANGELHO QUADRANGULAR | C28: EGS ENERGIA | E28: Adriana
A29: 67992899434 | B29: IGREJA DO EVANGELHO QUADRANGULAR | C29: EGS ENERGIA | E29: Adriana
A30: 67992021114 | B30: IGREJA DO EVANGELHO QUADRANGULAR | C30: EGS ENERGIA | E30: Adriana
A31: 67 992319530 | B31: IGREJA DO EVANGELHO QUADRANGULAR | C31: EGS ENERGIA | E31: Adriana
A32: 67998363594 | B32: IGREJA DO EVANGELHO QUADRANGULAR | C32: EGS ENERGIA | E32: Adriana
A33: 6796411024 | B33: IGREJA DO EVANGELHO QUADRANGULAR | C33: EGS ENERGIA | E33: Adriana
A34: 67999361728 | B34: IGREJA DO EVANGELHO QUADRANGULAR | C34: EGS ENERGIA | E34: Adriana
A35: 67991060202 | B35: IGREJA DO EVANGELHO QUADRANGULAR | C35: EGS ENERGIA | E35: Adriana
A36: 67999998719 | B36: IGREJA DO EVANGELHO QUADRANGULAR | C36: EGS ENERGIA | E36: Adriana
A37: 67 992491551 | B37: IGREJA DO EVANGELHO QUADRANGULAR | C37: EGS ENERGIA | E37: Adriana
A38: 67 993047635 | B38: IGREJA DO EVANGELHO QUADRANGULAR | C38: EGS ENERGIA | E38: Adriana
A39: 67996071169 | B39: IGREJA DO EVANGELHO QUADRANGULAR | C39: EGS ENERGIA | E39: Adriana
A40: 67996859014 | B40: IGREJA DO EVANGELHO QUADRANGULAR | C40: EGS ENERGIA | E40: Adriana
A41: 67991306665 | B41: IGREJA DO EVANGELHO QUADRANGULAR | C41: EGS ENERGIA | E41: Adriana
A42: 16 988508102 | B42: IGREJA DO EVANGELHO QUADRANGULAR | C42: EGS ENERGIA | E42: Adriana
A43: 67981263396 | B43: IGREJA DO EVANGELHO QUADRANGULAR | C43: EGS ENERGIA | E43: Adriana
A44: 67996687077 | B44: IGREJA DO EVANGELHO QUADRANGULAR | C44: EGS ENERGIA | E44: Adriana
A45: 67996983476 | B45: IGREJA DO EVANGELHO QUADRANGULAR | C45: EGS ENERGIA | E45: Adriana
A46: 67993249456 | B46: IGREJA DO EVANGELHO QUADRANGULAR | C46: EGS ENERGIA | E46: Adriana
A47: 67991133770 | B47: IGREJA DO EVANGELHO QUADRANGULAR | C47: EGS ENERGIA | E47: Adriana
A48: 67 998229474 | B48: IGREJA DO EVANGELHO QUADRANGULAR | C48: EGS ENERGIA | E48: Adriana
A49: 67 91751433 | B49: IGREJA DO EVANGELHO QUADRANGULAR | C49: EGS ENERGIA | E49: Adriana
A50: 67 984742936 | B50: IGREJA DO EVANGELHO QUADRANGULAR | C50: EGS ENERGIA | E50: Adriana
A51: 67992876000 | B51: IGREJA DO EVANGELHO QUADRANGULAR | C51: EGS ENERGIA | E51: Adriana
A52: 65999839279 | B52: IGREJA DO EVANGELHO QUADRANGULAR | C52: EGS ENERGIA | E52: Adriana
A53: 67998302932 | B53: IGREJA DO EVANGELHO QUADRANGULAR | C53: EGS ENERGIA | E53: Adriana

Sheet Faturamento
A1: Região | B1: Instalação | C1: Telefone | D1: CNPJ | E1: Distribuidora | F1: Razão Social | G1: Referência | H1: COD | I1: Fatura Disco Disponível? | J1: Créd. Consumido | K1: CUSTO_S_GD | L1: CUSTO_C_GD | M1: Status Faturamento | N1: Valor sem desconto | O1: Valor liberado | P1: Data emissão | Q1: Data Vencimento | R1: Valor emitido | S1: Motivo não emissão | T1: COD VALOR EMITIDO | U1: COD BOLETO | V1: Status Pagamento | W1: Valor Pago | X1: Multa/Juros | Y1: Data Pagamento | Z1: Estágio da Cobrança | AA1: CLIENTE (somente números) | AB1: CANAL (somente números) | AC1: NOME OU RAZÃO SOCIAL DO PAGADOR | AD1: CPF/CNPJ DO PAGADOR (digitar somente números entre apóstrofos ( ' ' )) | AE1: VALOR DO BOLETO (número com centavos separado por vírgula) | AF1: DATA DE VENCIMENTO (dd/mm/aaaa) | AG1: TEXTO QUE APARECERÁ NO CAMPO "INSTRUÇÕES" (opcional) | AH1: E-MAIL DO PAGADOR | AI1: Obs Planilha Rubia
A2: =VLOOKUP(B2,base!A:M,11,FALSE) -> TRIFÁSICO | B2: 10/237441-1 | C2: 0 | D2: 62955505017213 | E2: energisa_ms | F2: Igreja do Evangelho Quadrangular | G2: 45901 | H2: =Faturamento!$B836&Faturamento!$G836 -> 10/2338577-645658 | I2: SIM | J2: 0 | M2: Não emitido | N2: 0 | S2: Sem valor liberado para emissão | T2: 62955505017213 | V2: Não faturado | X2: =IF(Faturamento!$V879="Pago",IFERROR(W2-R2,0),0) -> 0
A3: =VLOOKUP(B3,base!A:M,11,FALSE) -> TRIFÁSICO | B3: 10/135237-6 | C3: 0 | D3: 62955505080098 | E3: energisa_ms | F3: Igreja do Evangelho Quadrangular | G3: 45901 | H3: =Faturamento!$B842&Faturamento!$G842 -> 10/142353-245689 | I3: SIM | J3: 0 | M3: Não emitido | N3: 0 | S3: Sem valor liberado para emissão | T3: 62955505080098 | V3: Não faturado | X3: =IF(Faturamento!$V880="Pago",IFERROR(W3-R3,0),0) -> 0
A4: =VLOOKUP(B4,base!A:M,11,FALSE) -> TRIFÁSICO | B4: 10/512142-1 | C4: Solicitação de distrato | D4: 62955505189340 | E4: energisa_ms | F4: Igreja do Evangelho Quadrangular | G4: 45901 | H4: =Faturamento!$B879&Faturamento!$G879 -> 10/104720-845717 | I4: SIM | J4: 0 | M4: Não emitido | N4: 0 | S4: Sem valor liberado para emissão | T4: 62955505189340 | V4: Não faturado | X4: =IF(Faturamento!$V888="Pago",IFERROR(W4-R4,0),0) -> 0
A5: =VLOOKUP(B5,base!A:M,11,FALSE) -> BIFÁSICO | B5: 10/31292-6 | C5: Solicitação de distrato | D5: 62955505016080 | E5: energisa_ms | F5: Igreja do Evangelho Quadrangular | G5: 45901 | H5: =Faturamento!$B883&Faturamento!$G883 -> 10/1081489-545717 | I5: SIM | J5: 0 | M5: Não emitido | N5: 0 | S5: Sem valor liberado para emissão | T5: 62955505016080 | V5: Não faturado | X5: =IF(Faturamento!$V889="Pago",IFERROR(W5-R5,0),0) -> 0
A6: =VLOOKUP(B6,base!A:M,11,FALSE) -> TRIFÁSICO | B6: 10/3054052-0 | C6: 0 | D6: 62955505312487 | E6: energisa_ms | F6: Igreja do Evangelho Quadrangular | G6: 45901 | H6: =Faturamento!$B888&Faturamento!$G888 -> 10/69319-245717 | I6: SIM | J6: 0 | M6: Não emitido | N6: 0 | S6: Sem valor liberado para emissão | T6: 62955505312487 | V6: Não faturado | X6: =IF(Faturamento!$V890="Pago",IFERROR(W6-R6,0),0) -> 0
A7: =VLOOKUP(B7,base!A:M,11,FALSE) -> TRIFÁSICO | B7: 10/505854-0 | C7: 0 | D7: 62955505887382 | E7: energisa_ms | F7: Igreja do Evangelho Quadrangular | G7: 45901 | H7: =Faturamento!$B890&Faturamento!$G890 -> 10/3139326-745717 | I7: SIM | J7: 0 | M7: Não emitido | N7: 0 | S7: Sem valor liberado para emissão | T7: 62955505887382 | V7: Não faturado | X7: =IF(Faturamento!$V892="Pago",IFERROR(W7-R7,0),0) -> 0
A8: =VLOOKUP(B8,base!A:M,11,FALSE) -> TRIFÁSICO | B8: 10/364440-8 | C8: 67991120875 | D8: 62955505015199 | E8: energisa_ms | F8: Igreja do Evangelho Quadrangular | G8: 45839 | H8: =Faturamento!$B619&Faturamento!$G619 -> 10/175073-645809 | I8: SIM | J8: 2565 | K8: 3099.7895 | L8: 2415.3816 | M8: =IF(Faturamento!$S619<>"","Não emitido",IF(Faturamento!$I619="NÃO","Pendente Fatura", IF(Faturamento!$R619<>"","Aprovado",IF(Faturamento!$O619<>0,"Pendente Emissão","Processo de Calculo")))) -> Aprovado | N8: 3021.3295 | O8: 2336.92 | P8: 45910 | Q8: 45920 | R8: 2336.92 | T8: 629555050151992336,92 | U8: 09/00012683468-6 | V8: Pago | W8: 2336.92 | X8: =IF(Faturamento!$V829="Pago",IFERROR(W8-R8,0),0) -> 0
A9: =VLOOKUP(B9,base!A:M,11,FALSE) -> TRIFÁSICO | B9: 10/364440-8 | C9: Inadimplência | D9: 62955505015199 | E9: energisa_ms | F9: Igreja do Evangelho Quadrangular | G9: 45870 | H9: =Faturamento!$B712&Faturamento!$G712 -> 10/24514-245839 | I9: SIM | J9: 2565 | K9: 3108.5835 | L9: 2433.0722 | M9: =IF(Faturamento!$S712<>"","Não emitido",IF(Faturamento!$I712="NÃO","Pendente Fatura", IF(Faturamento!$R712<>"","Aprovado",IF(Faturamento!$O712<>0,"Pendente Emissão","Processo de Calculo")))) -> Aprovado | N9: 2989.5035 | O9: 2313.99 | P9: 45910 | Q9: 45920 | R9: 2313.99 | T9: 629555050151992313,99 | U9: 09/00012749632-9 | V9: Pago | W9: 2313.99 | X9: =IF(Faturamento!$V828="Pago",IFERROR(W9-R9,0),0) -> 0
A10: =VLOOKUP(B10,base!A:M,11,FALSE) -> TRIFÁSICO | B10: 10/364440-8 | C10: Inadimplência | D10: 62955505015199 | E10: energisa_ms | F10: Igreja do Evangelho Quadrangular | G10: 45901 | H10: =Faturamento!$B804&Faturamento!$G804 -> 10/2605731-545627 | I10: SIM | J10: 2565 | K10: 3219.954 | L10: 2387.591 | M10: Aprovado | N10: 3099.134 | O10: 2266.77 | P10: 45933 | Q10: 45943 | R10: =O10 -> 2266.77 | T10: 629555050151992266,77 | U10: 09/00012851397-3 | V10: Pago | W10: =R10 -> 2266.77 | X10: =IF(Faturamento!$V827="Pago",IFERROR(W10-R10,0),0) -> 0
A11: =VLOOKUP(B11,base!A:M,11,FALSE) -> TRIFÁSICO | B11: 10/364440-8 | C11: 67991120875 | D11: 62955505015199 | E11: energisa_ms | F11: Igreja do Evangelho Quadrangular | G11: 45809 | H11: =Faturamento!$B530&Faturamento!$G530 -> 10/395471-645658 | I11: SIM | J11: 2579 | K11: 3065.79 | L11: 2361.0523 | M11: =IF(Faturamento!$S530<>"","Não emitido",IF(Faturamento!$I530="NÃO","Pendente Fatura", IF(Faturamento!$R530<>"","Aprovado",IF(Faturamento!$O530<>0,"Pendente Emissão","Processo de Calculo")))) -> Aprovado | N11: 2970.39 | O11: 2227.79 | P11: 45860 | Q11: 45871 | R11: 2227.79 | T11: 629555050151992227,79 | U11: 09/00012472737-9 | V11: Pago | W11: 2227.79 | X11: =IF(Faturamento!$V826="Pago",IFERROR(W11-R11,0),0) -> 0 | Y11: 05/08/2025
A12: =VLOOKUP(B12,base!A:M,11,FALSE) -> TRIFÁSICO | B12: 10/5202-7 | C12: 67 996469842 | D12: 62955505393207 | E12: energisa_ms | F12: Igreja do Evangelho Quadrangular | G12: 45717 | H12: =Faturamento!$B240&Faturamento!$G240 -> 10/63920-345931 | I12: SIM | J12: 2733 | K12: 3308.3 | L12: 2597.8525 | M12: =IF(Faturamento!$S240<>"","Não emitido",IF(Faturamento!$I240="NÃO","Pendente Fatura", IF(Faturamento!$R240<>"","Aprovado",IF(Faturamento!$O240<>0,"Pendente Emissão","Processo de Calculo")))) -> Aprovado | N12: 2841.79 | O12: 2131.34 | R12: 2131.34 | T12: 629555053932072131,34 | V12: Pago | W12: 2131.34 | X12: =IF(Faturamento!$V825="Pago",IFERROR(W12-R12,0),0) -> 0 | AI12: =VLOOKUP(B12,'[1]Conciliação - 032025'!$A:$L,12,FALSE) -> DEPÓSITO UNIFICADO ITAU - R$3.541,82 03/06/2025
A13: =VLOOKUP(B13,base!A:M,11,FALSE) -> TRIFÁSICO | B13: 10/364440-8 | C13: 67991120875 | D13: 62955505015199 | E13: energisa_ms | F13: Igreja do Evangelho Quadrangular | G13: 45748 | H13: =Faturamento!$B336&Faturamento!$G336 -> 10/129490-945717 | I13: SIM | J13: 2722 | K13: 3042.89 | L13: 2336.3525 | M13: =IF(Faturamento!$S336<>"","Não emitido",IF(Faturamento!$I336="NÃO","Pendente Fatura", IF(Faturamento!$R336<>"","Aprovado",IF(Faturamento!$O336<>0,"Pendente Emissão","Processo de Calculo")))) -> Aprovado | N13: 2826.15 | O13: 2119.61 | R13: 2119.61 | T13: 629555050151992119,61 | U13: #N/A | V13: Atrasado | W13: 0 | X13: =IF(Faturamento!$V152="Pago",IFERROR(W13-R13,0),0) -> -2119.61 | Z13: Cobrança Regular
A14: =VLOOKUP(B14,base!A:M,11,FALSE) -> TRIFÁSICO | B14: 10/364440-8 | C14: 67991120875 | D14: 62955505015199 | E14: energisa_ms | F14: Igreja do Evangelho Quadrangular | G14: 45717 | H14: =Faturamento!$B239&Faturamento!$G239 -> 10/40190-145658 | I14: SIM | J14: 2706 | K14: 3024.93 | L14: 2323.2125 | M14: =IF(Faturamento!$S239<>"","Não emitido",IF(Faturamento!$I239="NÃO","Pendente Fatura", IF(Faturamento!$R239<>"","Aprovado",IF(Faturamento!$O239<>0,"Pendente Emissão","Processo de Calculo")))) -> Aprovado | N14: 2806.87 | O14: 2105.15 | R14: 2105.15 | T14: 629555050151992105,15 | V14: Pago | W14: 2105.15 | X14: =IF(Faturamento!$V824="Pago",IFERROR(W14-R14,0),0) -> 0
A15: =VLOOKUP(B15,base!A:M,11,FALSE) -> TRIFÁSICO | B15: 10/364440-8 | C15: 67991120875 | D15: 62955505015199 | E15: energisa_ms | F15: Igreja do Evangelho Quadrangular | G15: 45689 | H15: =Faturamento!$B170&Faturamento!$G170 -> 10/1081489-545839 | I15: SIM | J15: 2675 | K15: 2986.01 | L15: 2292.3025 | M15: =IF(Faturamento!$S170<>"","Não emitido",IF(Faturamento!$I170="NÃO","Pendente Fatura", IF(Faturamento!$R170<>"","Aprovado",IF(Faturamento!$O170<>0,"Pendente Emissão","Processo de Calculo")))) -> Aprovado | N15: 2774.83 | O15: 2081.12 | R15: 2081.12 | T15: 629555050151992081,12 | V15: Pago | W15: 2081.12 | X15: =IF(Faturamento!$V823="Pago",IFERROR(W15-R15,0),0) -> 0
A16: =VLOOKUP(B16,base!A:M,11,FALSE) -> TRIFÁSICO | B16: 10/364440-8 | C16: 67991120875 | D16: 62955505015199 | E16: energisa_ms | F16: Igreja do Evangelho Quadrangular | G16: 45658 | H16: =Faturamento!$B74&Faturamento!$G74 -> 10/925970-645717 | I16: SIM | J16: 2468 | K16: 2959.61 | L16: 2270.875 | M16: =IF(Faturamento!$S74<>"","Não emitido",IF(Faturamento!$I74="NÃO","Pendente Fatura", IF(Faturamento!$R74<>"","Aprovado",IF(Faturamento!$O74<>0,"Pendente Emissão","Processo de Calculo")))) -> Aprovado | N16: 2754.94 | O16: 2066.21 | R16: 2066.21 | T16: 629555050151992066,21 | V16: Pago | W16: 2066.21 | X16: =IF(Faturamento!$V822="Pago",IFERROR(W16-R16,0),0) -> 0
A17: =VLOOKUP(B17,base!A:M,11,FALSE) -> TRIFÁSICO | B17: 10/364440-8 | C17: 67991120875 | D17: 62955505015199 | E17: energisa_ms | F17: Igreja do Evangelho Quadrangular | G17: 45778 | H17: =Faturamento!$B433&Faturamento!$G433 -> 10/1035655-845778 | I17: SIM | J17: 2659 | K17: 2986.81 | L17: 2298.085 | M17: =IF(Faturamento!$S433<>"","Não emitido",IF(Faturamento!$I433="NÃO","Pendente Fatura", IF(Faturamento!$R433<>"","Aprovado",IF(Faturamento!$O433<>0,"Pendente Emissão","Processo de Calculo")))) -> Aprovado | N17: 2754.9 | O17: 2066.18 | R17: 2066.18 | T17: 629555050151992066,18 | V17: Atrasado | W17: 0 | X17: =IF(Faturamento!$V174="Pago",IFERROR(W17-R17,0),0) -> -2066.18 | Z17: Cobrança Regular
A18: =VLOOKUP(B18,base!A:M,11,FALSE) -> TRIFÁSICO | B18: 10/5202-7 | C18: 67 996469842 | D18: 62955505016160 | E18: energisa_ms | F18: IGREJA DO EVANGELHO QUADRANGULAR | G18: 45931 | H18: =Faturamento!$B934&Faturamento!$G934 -> 10/2344751-945778 | I18: SIM | J18: 1901 | K18: 2715.2643 | L18: 2062.9085 | M18: Aprovado | N18: 2332.5143 | O18: 1680.16 | P18: 45967 | Q18: 45974 | R18: 1680.16 | T18: =D18&R18 -> 629555050161601680,16 | U18: 09/00013026927-5 | V18: Pago | W18: =R18 -> 1680.16 | X18: =IF(Faturamento!$V936="Pago",IFERROR(W18-R18,0),0) -> 0
A19: =VLOOKUP(B19,base!A:M,11,FALSE) -> TRIFÁSICO | B19: 10/5202-7 | C19: 67 996469842 | D19: 62955505393207 | E19: energisa_ms | F19: Igreja do Evangelho Quadrangular | G19: 45748 | H19: =Faturamento!$B337&Faturamento!$G337 -> 10/109074-545748 | I19: SIM | J19: 2042 | K19: 2540.49 | L19: 1993.31 | M19: =IF(Faturamento!$S337<>"","Não emitido",IF(Faturamento!$I337="NÃO","Pendente Fatura", IF(Faturamento!$R337<>"","Aprovado",IF(Faturamento!$O337<>0,"Pendente Emissão","Processo de Calculo")))) -> Aprovado | N19: 2188.72 | O19: 1641.54 | R19: 1641.54 | T19: 629555053932071641,54 | V19: Pago | W19: 1641.54 | X19: =IF(Faturamento!$V821="Pago",IFERROR(W19-R19,0),0) -> 0
A20: =VLOOKUP(B20,base!A:M,11,FALSE) -> TRIFÁSICO | B20: 10/5202-7 | C20: 67 996469842 | D20: 62955505393207 | E20: energisa_ms | F20: Igreja do Evangelho Quadrangular | G20: 45689 | H20: =Faturamento!$B177&Faturamento!$G177 -> 10/3092868-345931 | I20: SIM | J20: 1810 | K20: 2324.4 | L20: 1854.24 | M20: =IF(Faturamento!$S177<>"","Não emitido",IF(Faturamento!$I177="NÃO","Pendente Fatura", IF(Faturamento!$R177<>"","Aprovado",IF(Faturamento!$O177<>0,"Pendente Emissão","Processo de Calculo")))) -> Aprovado | N20: 1880.64 | O20: 1410.48 | R20: 1410.48 | T20: 629555053932071410,48 | V20: Pago | W20: 1410.48 | X20: =IF(Faturamento!$V820="Pago",IFERROR(W20-R20,0),0) -> 0
A21: =VLOOKUP(B21,base!A:M,11,FALSE) -> TRIFÁSICO | B21: 10/2605731-5 | C21: 67992637973 | D21: 62955505017213 | E21: energisa_ms | F21: Igreja do Evangelho Quadrangular | G21: 45658 | H21: =Faturamento!$B67&Faturamento!$G67 -> 10/202838-945901 | I21: SIM | J21: 1682 | K21: 2029.18 | L21: 1593.43 | M21: =IF(Faturamento!$S67<>"","Não emitido",IF(Faturamento!$I67="NÃO","Pendente Fatura", IF(Faturamento!$R67<>"","Aprovado",IF(Faturamento!$O67<>0,"Pendente Emissão","Processo de Calculo")))) -> Aprovado | N21: 1743 | O21: 1307.25 | R21: 1307.25 | T21: 629555050172131307,25 | V21: Pago | W21: 1307.25 | X21: =IF(Faturamento!$V819="Pago",IFERROR(W21-R21,0),0) -> 0
A22: =VLOOKUP(B22,base!A:M,11,FALSE) -> TRIFÁSICO | B22: 10/364440-8 | C22: 67991120875 | D22: 62955505015199 | E22: energisa_ms | F22: IGREJA DO EVANGELHO QUADRANGULAR | G22: 45931 | H22: =Faturamento!$B935&Faturamento!$G935 -> 10/31292-645778 | I22: SIM | J22: 1399 | K22: 3275.3774 | L22: 2794.8836 | M22: Aprovado | N22: 1718.0174 | O22: 1237.52 | P22: 45967 | Q22: 45974 | R22: 1237.52 | T22: =D22&R22 -> 629555050151991237,52 | U22: 09/00013026929-1 | V22: Pago | W22: =R22 -> 1237.52 | X22: =IF(Faturamento!$V937="Pago",IFERROR(W22-R22,0),0) -> 0
A23: =VLOOKUP(B23,base!A:M,11,FALSE) -> TRIFÁSICO | B23: 10/5202-7 | C23: 67 996469842 | D23: 62955505393207 | E23: energisa_ms | F23: Igreja do Evangelho Quadrangular | G23: 45778 | H23: =Faturamento!$B434&Faturamento!$G434 -> 10/162736-345748 | I23: SIM | J23: 1458 | K23: 2221.7649 | L23: 1810.2987 | M23: =IF(Faturamento!$S434<>"","Não emitido",IF(Faturamento!$I434="NÃO","Pendente Fatura", IF(Faturamento!$R434<>"","Aprovado",IF(Faturamento!$O434<>0,"Pendente Emissão","Processo de Calculo")))) -> Aprovado | N23: 1645.8649 | O23: 1234.4 | R23: 1234.4 | T23: 629555053932071234,4 | V23: Pago | W23: 1234.4 | X23: =IF(Faturamento!$V818="Pago",IFERROR(W23-R23,0),0) -> 0
A24: =VLOOKUP(B24,base!A:M,11,FALSE) -> TRIFÁSICO | B24: 10/2605731-5 | C24: 67992637973 | D24: 62955505017213 | E24: energisa_ms | F24: Igreja do Evangelho Quadrangular | G24: 45689 | H24: =Faturamento!$B164&Faturamento!$G164 -> 10/399338-345778 | I24: SIM | J24: 1500 | K24: 1894.11 | L24: 1506.335 | M24: =IF(Faturamento!$S164<>"","Não emitido",IF(Faturamento!$I164="NÃO","Pendente Fatura", IF(Faturamento!$R164<>"","Aprovado",IF(Faturamento!$O164<>0,"Pendente Emissão","Processo de Calculo")))) -> Aprovado | N24: 1551.1 | O24: 1163.33 | R24: 1163.33 | T24: 629555050172131163,33 | V24: Pago | W24: 1163.33 | X24: =IF(Faturamento!$V817="Pago",IFERROR(W24-R24,0),0) -> 0
A25: =VLOOKUP(B25,base!A:M,11,FALSE) -> TRIFÁSICO | B25: 10/2599101-9 | C25: 67991120875 | D25: 62955505379395 | E25: energisa_ms | F25: Igreja do Evangelho Quadrangular | G25: 45717 | H25: =Faturamento!$B276&Faturamento!$G276 -> 10/76927-345658 | I25: SIM | J25: 1430 | K25: 1598.22 | L25: 1231.5075 | M25: =IF(Faturamento!$S276<>"","Não emitido",IF(Faturamento!$I276="NÃO","Pendente Fatura", IF(Faturamento!$R276<>"","Aprovado",IF(Faturamento!$O276<>0,"Pendente Emissão","Processo de Calculo")))) -> Aprovado | N25: 1466.85 | O25: 1100.14 | R25: 1100.14 | T25: 629555053793951100,14 | V25: Pago | W25: 1100.14 | X25: =IF(Faturamento!$V816="Pago",IFERROR(W25-R25,0),0) -> 0
A26: =VLOOKUP(B26,base!A:M,11,FALSE) -> TRIFÁSICO | B26: 10/2605731-5 | C26: 67992637973 | D26: 62955505017213 | E26: energisa_ms | F26: IGREJA DO EVANGELHO QUADRANGULAR | G26: 45931 | H26: =Faturamento!$B938&Faturamento!$G938 -> 10/113971-645809 | I26: SIM | J26: 1216 | K26: 1692.8924 | L26: 1284.0986 | M26: Aprovado | N26: 1461.6524 | O26: 1052.86 | P26: 45967 | Q26: 45974 | R26: 1052.86 | T26: =D26&R26 -> 629555050172131052,86 | U26: 09/00013026934-1 | V26: Pago | W26: =R26 -> 1052.86 | X26: =IF(Faturamento!$V940="Pago",IFERROR(W26-R26,0),0) -> 0
A27: =VLOOKUP(B27,base!A:M,11,FALSE) -> TRIFÁSICO | B27: 10/2599101-9 | C27: 67991120875 | D27: 62955505379395 | E27: energisa_ms | F27: IGREJA DO EVANGELHO QUADRANGULAR | G27: 45931 | H27: =Faturamento!$B940&Faturamento!$G940 -> 10/1433087-245809 | I27: SIM | J27: 1171 | K27: 1568.9311 | L27: 1165.3788 | M27: Aprovado | N27: 1442.9111 | O27: 1039.36 | P27: 45967 | Q27: 45974 | R27: 1039.36 | T27: =D27&R27 -> 629555053793951039,36 | U27: 09/00013026937-4 | V27: Pago | W27: =R27 -> 1039.36 | X27: =IF(Faturamento!$V942="Pago",IFERROR(W27-R27,0),0) -> 0
A28: =VLOOKUP(B28,base!A:M,11,FALSE) -> TRIFÁSICO | B28: 10/5202-7 | C28: 67 996469842 | D28: 62955505393207 | E28: energisa_ms | F28: Igreja do Evangelho Quadrangular | G28: 45658 | H28: =Faturamento!$B81&Faturamento!$G81 -> 10/1674177-945931 | I28: SIM | J28: 1233 | K28: 2315.08 | L28: 1970.9925 | M28: =IF(Faturamento!$S81<>"","Não emitido",IF(Faturamento!$I81="NÃO","Pendente Fatura", IF(Faturamento!$R81<>"","Aprovado",IF(Faturamento!$O81<>0,"Pendente Emissão","Processo de Calculo")))) -> Aprovado | N28: 1376.35 | O28: 1032.26 | R28: 1032.26 | T28: 629555053932071032,26 | V28: Pago | W28: 1032.26 | X28: =IF(Faturamento!$V815="Pago",IFERROR(W28-R28,0),0) -> 0
A29: =VLOOKUP(B29,base!A:M,11,FALSE) -> TRIFÁSICO | B29: 10/18015-8 | C29: 67996266684 | D29: 62955505016080 | E29: energisa_ms | F29: IGREJA DO EVANGELHO QUADRANGULAR | G29: 45931 | H29: =Faturamento!$B936&Faturamento!$G936 -> 10/18015-845809 | I29: SIM | J29: 1150 | K29: 1509.535 | L29: 1121.1263 | M29: Aprovado | N29: 1388.765 | O29: 1000.36 | P29: 45967 | Q29: 45974 | R29: 1000.36 | T29: =D29&R29 -> 629555050160801000,36 | U29: 09/00013026931-7 | V29: Pago | W29: =R29 -> 1000.36 | X29: =IF(Faturamento!$V938="Pago",IFERROR(W29-R29,0),0) -> 0
A30: =VLOOKUP(B30,base!A:M,11,FALSE) -> #N/A | B30: 10/3170252-5 | C30: #N/A | D30: 62955505035629 | E30: energisa_ms | F30: Igreja do Evangelho Quadrangular | G30: 45717 | H30: =Faturamento!$B282&Faturamento!$G282 -> 10/127464-645870 | I30: SIM | J30: 1313 | M30: =IF(Faturamento!$S282<>"","Não emitido",IF(Faturamento!$I282="NÃO","Pendente Fatura", IF(Faturamento!$R282<>"","Aprovado",IF(Faturamento!$O282<>0,"Pendente Emissão","Processo de Calculo")))) -> Aprovado | N30: 1278.94 | O30: 959.21 | S30: não emitido pela EGS | T30: 62955505035629 | V30: Não faturado | W30: 0 | X30: =IF(Faturamento!$V111="Pago",IFERROR(W30-R30,0),0) -> 0
A31: =VLOOKUP(B31,base!A:M,11,FALSE) -> TRIFÁSICO | B31: 10/18015-8 | C31: 67996266684 | D31: 62955505016080 | E31: energisa_ms | F31: Igreja do Evangelho Quadrangular | G31: 45658 | H31: =Faturamento!$B58&Faturamento!$G58 -> 10/2605731-545870 | I31: SIM | J31: 1161 | K31: 1414.3 | L31: 1100.9575 | M31: =IF(Faturamento!$S58<>"","Não emitido",IF(Faturamento!$I58="NÃO","Pendente Fatura", IF(Faturamento!$R58<>"","Aprovado",IF(Faturamento!$O58<>0,"Pendente Emissão","Processo de Calculo")))) -> Aprovado | N31: 1253.37 | O31: 940.03 | R31: 940.03 | T31: 62955505016080940,03 | V31: Pago | W31: 940.03 | X31: =IF(Faturamento!$V814="Pago",IFERROR(W31-R31,0),0) -> 0 | AA31: 283032 | AB31: 502 | AC31: Igreja do Evangelho Quadrangular | AD31: '62955505239119' | AE31: 64.91 | AG31: A Unidade Consumidora 10/341308-5 economizou R$21,64 na fatura referente à jun/2025 consumindo 86 kWh em créditos de energia renovável conforme fatura de energia. A economia foi de 25% em relação ao que seria pago para a Energisa considerando os créditos consumidos. Atenção: Mantenha as contas da Energisa em dia para evitar cortes. | AH31: monicadossantosfonseca@hotmail.com
A32: =VLOOKUP(B32,base!A:M,11,FALSE) -> TRIFÁSICO | B32: 10/2605731-5 | C32: 0 | D32: 62955505017213 | E32: energisa_ms | F32: Igreja do Evangelho Quadrangular | G32: 45901 | H32: =Faturamento!$B807&Faturamento!$G807 -> 10/3005226-045627 | I32: SIM | J32: 1005 | K32: 1446.0075 | L32: 1119.9073 | M32: Aprovado | N32: 1214.1675 | O32: 888.07 | P32: 45933 | Q32: 45943 | R32: =O32 -> 888.07 | T32: 62955505017213888,07 | U32: 09/00012851400-5 | V32: Pago | W32: =R32 -> 888.07 | X32: =IF(Faturamento!$V813="Pago",IFERROR(W32-R32,0),0) -> 0
A33: =VLOOKUP(B33,base!A:M,11,FALSE) -> TRIFÁSICO | B33: 10/18015-8 | C33: 0 | D33: 62955505016080 | E33: energisa_ms | F33: Igreja do Evangelho Quadrangular | G33: 45901 | H33: =Faturamento!$B805&Faturamento!$G805 -> 10/276283-945627 | I33: SIM | J33: 992 | K33: 1319.3932 | L33: 997.48403 | M33: Aprovado | N33: 1198.5632 | O33: 876.65 | P33: 45933 | Q33: 45943 | R33: =O33 -> 876.65 | T33: 62955505016080876,65 | U33: 09/00012851398-1 | V33: Pago | W33: =R33 -> 876.65 | X33: =IF(Faturamento!$V812="Pago",IFERROR(W33-R33,0),0) -> 0
A34: =VLOOKUP(B34,base!A:M,11,FALSE) -> TRIFÁSICO | B34: 10/202838-9 | C34: 67992637973 | D34: 62955505016403 | E34: energisa_ms | F34: Igreja do Evangelho Quadrangular | G34: 45717 | H34: =Faturamento!$B277&Faturamento!$G277 -> 10/13786-945931 | I34: SIM | J34: 1120 | K34: 1458.59 | L34: 1170.5725 | M34: =IF(Faturamento!$S277<>"","Não emitido",IF(Faturamento!$I277="NÃO","Pendente Fatura", IF(Faturamento!$R277<>"","Aprovado",IF(Faturamento!$O277<>0,"Pendente Emissão","Processo de Calculo")))) -> Aprovado | N34: 1152.07 | O34: 864.05 | R34: 864.05 | T34: 62955505016403864,05 | V34: Pago | W34: 864.05 | X34: =IF(Faturamento!$V811="Pago",IFERROR(W34-R34,0),0) -> 0
A35: =VLOOKUP(B35,base!A:M,11,FALSE) -> #N/A | B35: 10/3170252-5 | C35: #N/A | D35: 62955505035629 | E35: energisa_ms | F35: Igreja do Evangelho Quadrangular | G35: 45658 | H35: =Faturamento!$B141&Faturamento!$G141 -> 10/202838-945839 | I35: SIM | J35: 1119 | K35: 1431.63 | L35: 1152.2675 | M35: =IF(Faturamento!$S141<>"","Não emitido",IF(Faturamento!$I141="NÃO","Pendente Fatura", IF(Faturamento!$R141<>"","Aprovado",IF(Faturamento!$O141<>0,"Pendente Emissão","Processo de Calculo")))) -> Aprovado | N35: 1117.45 | O35: 838.09 | R35: 838.09 | S35: Cobrança indevida (Planilha Rubia) | T35: 62955505035629838,09 | V35: Cancelado | W35: 0 | X35: =IF(Faturamento!$V61="Pago",IFERROR(W35-R35,0),0) -> -838.09
A36: =VLOOKUP(B36,base!A:M,11,FALSE) -> TRIFÁSICO | B36: 10/2599101-9 | C36: 0 | D36: 62955505379395 | E36: energisa_ms | F36: Igreja do Evangelho Quadrangular | G36: 45901 | H36: =Faturamento!$B809&Faturamento!$G809 -> 10/3092868-345627 | I36: SIM | J36: 909 | K36: 1221.2946 | L36: 926.3692 | M36: Aprovado | N36: 1098.0946 | O36: 803.17 | P36: 45933 | Q36: 45943 | R36: =O36 -> 803.17 | T36: 62955505379395803,17 | U36: 09/00012851402-1 | V36: Pago | W36: =R36 -> 803.17 | X36: =IF(Faturamento!$V810="Pago",IFERROR(W36-R36,0),0) -> 0
A37: =VLOOKUP(B37,base!A:M,11,FALSE) -> #N/A | B37: 10/2247256-7 | C37: #N/A | D37: 62955505015199 | E37: energisa_ms | F37: Igreja do Evangelho Quadrangular | G37: 45689 | H37: =Faturamento!$B186&Faturamento!$G186 -> 10/8777-545778 | I37: SIM | J37: 936 | K37: 1270.54 | L37: 1024.3025 | M37: =IF(Faturamento!$S186<>"","Não emitido",IF(Faturamento!$I186="NÃO","Pendente Fatura", IF(Faturamento!$R186<>"","Aprovado",IF(Faturamento!$O186<>0,"Pendente Emissão","Processo de Calculo")))) -> Aprovado | N37: 984.95 | O37: 738.71 | R37: 738.71 | T37: 62955505015199738,71 | V37: Atrasado | W37: 0 | X37: =IF(Faturamento!$V66="Pago",IFERROR(W37-R37,0),0) -> -738.71 | Z37: Cobrança Regular | AI37: =VLOOKUP(B37,'[2]Conciliação - 022025'!$A:$L,12,FALSE) -> VALOR DEVIDO - Cancelamento via email dia 23/04, tenho tudo formalizado por whatsapp com Danilo Silva
A38: =VLOOKUP(B38,base!A:M,11,FALSE) -> TRIFÁSICO | B38: 10/202838-9 | C38: 67992637973 | D38: 62955505016403 | E38: energisa_ms | F38: Igreja do Evangelho Quadrangular | G38: 45689 | H38: =Faturamento!$B158&Faturamento!$G158 -> 10/3139326-745931 | I38: SIM | J38: 957 | K38: 1253.95 | L38: 1008.1475 | M38: =IF(Faturamento!$S158<>"","Não emitido",IF(Faturamento!$I158="NÃO","Pendente Fatura", IF(Faturamento!$R158<>"","Aprovado",IF(Faturamento!$O158<>0,"Pendente Emissão","Processo de Calculo")))) -> Aprovado | N38: 983.21 | O38: 737.41 | R38: 737.41 | T38: 62955505016403737,41 | V38: Pago | W38: 737.41 | X38: =IF(Faturamento!$V809="Pago",IFERROR(W38-R38,0),0) -> 0
A39: =VLOOKUP(B39,base!A:M,11,FALSE) -> TRIFÁSICO | B39: 10/18015-8 | C39: 67996266684 | D39: 62955505016080 | E39: energisa_ms | F39: Igreja do Evangelho Quadrangular | G39: 45689 | H39: =Faturamento!$B155&Faturamento!$G155 -> 10/72605-945931 | I39: SIM | J39: 875 | K39: 1044.82 | L39: 809.205 | M39: =IF(Faturamento!$S155<>"","Não emitido",IF(Faturamento!$I155="NÃO","Pendente Fatura", IF(Faturamento!$R155<>"","Aprovado",IF(Faturamento!$O155<>0,"Pendente Emissão","Processo de Calculo")))) -> Aprovado | N39: 942.46 | O39: 706.85 | R39: 706.85 | T39: 62955505016080706,85 | V39: Pago | W39: 706.85 | X39: =IF(Faturamento!$V808="Pago",IFERROR(W39-R39,0),0) -> 0
A40: =VLOOKUP(B40,base!A:M,11,FALSE) -> TRIFÁSICO | B40: 10/2599101-9 | C40: 67991120875 | D40: 62955505379395 | E40: energisa_ms | F40: Igreja do Evangelho Quadrangular | G40: 45748 | H40: =Faturamento!$B373&Faturamento!$G373 -> 10/1130988-745901 | I40: SIM | J40: 897 | K40: 1038.33 | L40: 803.3325 | M40: =IF(Faturamento!$S373<>"","Não emitido",IF(Faturamento!$I373="NÃO","Pendente Fatura", IF(Faturamento!$R373<>"","Aprovado",IF(Faturamento!$O373<>0,"Pendente Emissão","Processo de Calculo")))) -> Aprovado | N40: 939.99 | O40: 704.99 | R40: 704.99 | T40: 62955505379395704,99 | V40: Pago | W40: 704.99 | X40: =IF(Faturamento!$V807="Pago",IFERROR(W40-R40,0),0) -> 0
A41: =VLOOKUP(B41,base!A:M,11,FALSE) -> TRIFÁSICO | B41: 10/5202-7 | C41: 67 996469842 | D41: 62955505393207 | E41: energisa_ms | F41: Igreja do Evangelho Quadrangular | G41: 45809 | H41: =Faturamento!$B531&Faturamento!$G531 -> 10/156956-545901 | I41: SIM | J41: 777 | K41: 1804.9056 | L41: 1591.0267 | M41: =IF(Faturamento!$S531<>"","Não emitido",IF(Faturamento!$I531="NÃO","Pendente Fatura", IF(Faturamento!$R531<>"","Aprovado",IF(Faturamento!$O531<>0,"Pendente Emissão","Processo de Calculo")))) -> Aprovado | N41: 901.47565 | O41: 676.11 | P41: 45860 | Q41: 45871 | R41: 676.11 | T41: 62955505393207676,11 | U41: 09/00012472738-7 | V41: Pago | W41: 676.11 | X41: =IF(Faturamento!$V806="Pago",IFERROR(W41-R41,0),0) -> 0 | Y41: 01/08/2025
A42: =VLOOKUP(B42,base!A:M,11,FALSE) -> TRIFÁSICO | B42: 10/5202-7 | C42: 0 | D42: 62955505016160 | E42: energisa_ms | F42: Igreja do Evangelho Quadrangular | G42: 45901 | H42: =Faturamento!$B803&Faturamento!$G803 -> 10/2599101-945627 | I42: SIM | J42: 765 | K42: 1196.3859 | L42: 948.15531 | M42: Aprovado | N42: 924.23586 | O42: 676.01 | P42: 45933 | Q42: 45943 | R42: =O42 -> 676.01 | T42: 62955505016160676,01 | U42: 09/00012851396-5 | V42: Pago | W42: =R42 -> 676.01 | X42: =IF(Faturamento!$V805="Pago",IFERROR(W42-R42,0),0) -> 0
A43: =VLOOKUP(B43,base!A:M,11,FALSE) -> TRIFÁSICO | B43: 10/191945-5 | C43: 67 81355403 | D43: 62955505215791 | E43: energisa_ms | F43: IGREJA DO EVANGELHO QUADRANGULAR | G43: 45931 | H43: =Faturamento!$B941&Faturamento!$G941 -> 10/452884-045809 | I43: SIM | J43: 772 | K43: 1233.0264 | L43: 973.53822 | M43: Aprovado | N43: 927.8064 | O43: 668.32 | P43: 45967 | Q43: 45974 | R43: 668.32 | T43: =D43&R43 -> 62955505215791668,32 | U43: 09/00013026938-2 | V43: Pago | W43: =R43 -> 668.32 | X43: =IF(Faturamento!$V943="Pago",IFERROR(W43-R43,0),0) -> 0
A44: =VLOOKUP(B44,base!A:M,11,FALSE) -> TRIFÁSICO | B44: 10/29964-4 | C44: 67996266684 | D44: 62955505067660 | E44: energisa_ms | F44: Igreja do Evangelho Quadrangular | G44: 45778 | H44: =Faturamento!$B437&Faturamento!$G437 -> 10/399338-345839 | I44: SIM | J44: 762 | K44: 948.50892 | L44: 738.74419 | M44: =IF(Faturamento!$S437<>"","Não emitido",IF(Faturamento!$I437="NÃO","Pendente Fatura", IF(Faturamento!$R437<>"","Aprovado",IF(Faturamento!$O437<>0,"Pendente Emissão","Processo de Calculo")))) -> Aprovado | N44: 839.05892 | O44: 629.29 | R44: 629.29 | T44: 62955505067660629,29 | V44: Pago | W44: 629.29 | X44: =IF(Faturamento!$V804="Pago",IFERROR(W44-R44,0),0) -> 0
A45: =VLOOKUP(B45,base!A:M,11,FALSE) -> #N/A | B45: 10/3170252-5 | C45: #N/A | D45: 62955505035629 | E45: energisa_ms | F45: Igreja do Evangelho Quadrangular | G45: 45689 | H45: =Faturamento!$B185&Faturamento!$G185 -> 10/532723-445689 | I45: SIM | J45: 849 | K45: 1118.32 | L45: 911.575 | M45: =IF(Faturamento!$S185<>"","Não emitido",IF(Faturamento!$I185="NÃO","Pendente Fatura", IF(Faturamento!$R185<>"","Aprovado",IF(Faturamento!$O185<>0,"Pendente Emissão","Processo de Calculo")))) -> Aprovado | N45: 826.98 | O45: 620.24 | R45: 620.24 | T45: 62955505035629620,24 | V45: Cancelado | W45: NÃO IRA PAGAR | X45: =IF(Faturamento!$V830="Pago",IFERROR(W45-R45,0),0) -> 0 | AI45: =VLOOKUP(B45,'[2]Conciliação - 022025'!$A:$L,12,FALSE) -> COBRANÇA INDEVIDA - Vamos cancelar
A46: =VLOOKUP(B46,base!A:M,11,FALSE) -> TRIFÁSICO | B46: 10/2599101-9 | C46: 67991120875 | D46: 62955505379395 | E46: energisa_ms | F46: Igreja do Evangelho Quadrangular | G46: 45689 | H46: =Faturamento!$B163&Faturamento!$G163 -> 10/191945-545839 | I46: SIM | J46: 804 | K46: 946.01 | L46: 739.95 | M46: =IF(Faturamento!$S163<>"","Não emitido",IF(Faturamento!$I163="NÃO","Pendente Fatura", IF(Faturamento!$R163<>"","Aprovado",IF(Faturamento!$O163<>0,"Pendente Emissão","Processo de Calculo")))) -> Aprovado | N46: 824.24 | O46: 618.18 | R46: 618.18 | T46: 62955505379395618,18 | V46: Pago | W46: 618.18 | X46: =IF(Faturamento!$V803="Pago",IFERROR(W46-R46,0),0) -> 0
A47: =VLOOKUP(B47,base!A:M,11,FALSE) -> TRIFÁSICO | B47: 10/29964-4 | C47: 67996266684 | D47: 62955505067660 | E47: energisa_ms | F47: IGREJA DO EVANGELHO QUADRANGULAR | G47: 45931 | H47: =Faturamento!$B943&Faturamento!$G943 -> 10/135237-645809 | I47: SIM | J47: 697 | K47: 973.7989 | L47: 735.62158 | M47: Aprovado | N47: 851.6089 | O47: 613.43 | P47: 45967 | Q47: 45974 | R47: 613.43 | T47: =D47&R47 -> 62955505067660613,43 | U47: 09/00013026942-4 | V47: Pago | W47: =R47 -> 613.43 | X47: =IF(Faturamento!$V945="Pago",IFERROR(W47-R47,0),0) -> 0
A48: =VLOOKUP(B48,base!A:M,11,FALSE) -> TRIFÁSICO | B48: 10/202838-9 | C48: 67992637973 | D48: 62955505016403 | E48: energisa_ms | F48: IGREJA DO EVANGELHO QUADRANGULAR | G48: 45931 | H48: =Faturamento!$B937&Faturamento!$G937 -> 10/513413-545809 | I48: SIM | J48: 700 | K48: 1154.79 | L48: 917.09621 | M48: Aprovado | N48: 849.88 | O48: 612.29 | P48: 45967 | Q48: 45974 | R48: 612.29 | T48: =D48&R48 -> 62955505016403612,29 | U48: 09/00013026932-5 | V48: Pago | W48: =R48 -> 612.29 | X48: =IF(Faturamento!$V939="Pago",IFERROR(W48-R48,0),0) -> 0
A49: =VLOOKUP(B49,base!A:M,11,FALSE) -> TRIFÁSICO | B49: 10/18015-8 | C49: 0 | D49: 62955505016080 | E49: energisa_ms | F49: Igreja do Evangelho Quadrangular | G49: 45870 | H49: =Faturamento!$B714&Faturamento!$G714 -> 10/218777-145809 | I49: SIM | J49: 663 | K49: 905.5236 | L49: 727.72987 | M49: =IF(Faturamento!$S714<>"","Não emitido",IF(Faturamento!$I714="NÃO","Pendente Fatura", IF(Faturamento!$R714<>"","Aprovado",IF(Faturamento!$O714<>0,"Pendente Emissão","Processo de Calculo")))) -> Aprovado | N49: 786.8336 | O49: 609.04 | P49: 45910 | Q49: 45920 | R49: 609.04 | T49: 62955505016080609,04 | U49: 09/00012749634-5 | V49: Pago | W49: 609.04 | X49: =IF(Faturamento!$V802="Pago",IFERROR(W49-R49,0),0) -> 0
A50: =VLOOKUP(B50,base!A:M,11,FALSE) -> TRIFÁSICO | B50: 10/2605731-5 | C50: 67992637973 | D50: 62955505017213 | E50: energisa_ms | F50: Igreja do Evangelho Quadrangular | G50: 45717 | H50: =Faturamento!$B279&Faturamento!$G279 -> 10/3092868-345658 | I50: SIM | J50: 722 | K50: 1190.35 | L50: 988.865 | M50: =IF(Faturamento!$S279<>"","Não emitido",IF(Faturamento!$I279="NÃO","Pendente Fatura", IF(Faturamento!$R279<>"","Aprovado",IF(Faturamento!$O279<>0,"Pendente Emissão","Processo de Calculo")))) -> Aprovado | N50: 805.94 | O50: 604.46 | R50: 604.46 | T50: 62955505017213604,46 | V50: Pago | W50: 604.46 | X50: =IF(Faturamento!$V801="Pago",IFERROR(W50-R50,0),0) -> 0
A51: =VLOOKUP(B51,base!A:M,11,FALSE) -> TRIFÁSICO | B51: 10/202838-9 | C51: 67992637973 | D51: 62955505016403 | E51: energisa_ms | F51: Igreja do Evangelho Quadrangular | G51: 45778 | H51: =Faturamento!$B471&Faturamento!$G471 -> 10/239312-245809 | I51: SIM | J51: 700 | K51: 1093.93 | L51: 895.25 | M51: =IF(Faturamento!$S471<>"","Não emitido",IF(Faturamento!$I471="NÃO","Pendente Fatura", IF(Faturamento!$R471<>"","Aprovado",IF(Faturamento!$O471<>0,"Pendente Emissão","Processo de Calculo")))) -> Aprovado | N51: 794.72 | O51: 596.04 | R51: 596.04 | T51: 62955505016403596,04 | V51: Pago | W51: 596.04 | X51: =IF(Faturamento!$V800="Pago",IFERROR(W51-R51,0),0) -> 0
A52: =VLOOKUP(B52,base!A:M,11,FALSE) -> #N/A | B52: 10/3170252-5 | C52: #N/A | D52: #ND | E52: energisa_ms | F52: IGREJA DO EVANGELHO QUADRANGULAR | G52: 45931 | H52: =Faturamento!$B977&Faturamento!$G977 -> 10/3054052-045870 | I52: SIM | J52: 833 | M52: Não emitido | N52: 817.37 | O52: 588.77 | P52: - | Q52: - | R52: - | S52: Pendente dado cadastral | T52: =D52&R52 -> #ND- | U52: #N/A | V52: Não faturado | X52: =IF(Faturamento!$V979="Pago",IFERROR(W52-R52,0),0) -> 0
A53: =VLOOKUP(B53,base!A:M,11,FALSE) -> TRIFÁSICO | B53: 10/191945-5 | C53: 67 81355403 | D53: 62955505215791 | E53: energisa_ms | F53: Igreja do Evangelho Quadrangular | G53: 45658 | H53: =Faturamento!$B59&Faturamento!$G59 -> 10/191945-545901 | I53: SIM | J53: 718 | K53: 1173.96 | L53: 979.17 | M53: =IF(Faturamento!$S59<>"","Não emitido",IF(Faturamento!$I59="NÃO","Pendente Fatura", IF(Faturamento!$R59<>"","Aprovado",IF(Faturamento!$O59<>0,"Pendente Emissão","Processo de Calculo")))) -> Aprovado | N53: 779.16 | O53: 584.37 | R53: 584.37 | T53: 62955505215791584,37 | V53: Pago | W53: 584.37 | X53: =IF(Faturamento!$V799="Pago",IFERROR(W53-R53,0),0) -> 0 | AA53: 283032 | AB53: 502 | AC53: Igreja do Evangelho Quadrangular | AD53: '62955505335851' | AE53: 59.09 | AG53: A Unidade Consumidora 10/1288241-1 economizou R$19,7 na fatura referente à jun/2025 consumindo 79 kWh em créditos de energia renovável conforme fatura de energia. A economia foi de 25% em relação ao que seria pago para a Energisa considerando os créditos consumidos. Atenção: Mantenha as contas da Energisa em dia para evitar cortes. | AH53: regiao359@gmail.com
A54: =VLOOKUP(B54,base!A:M,11,FALSE) -> TRIFÁSICO | B54: 10/29964-4 | C54: 67996266684 | D54: 62955505067660 | E54: energisa_ms | F54: Igreja do Evangelho Quadrangular | G54: 45689 | H54: =Faturamento!$B166&Faturamento!$G166 -> 10/3030784-745748 | I54: SIM | J54: 738 | K54: 863.99 | L54: 672.01 | M54: =IF(Faturamento!$S166<>"","Não emitido",IF(Faturamento!$I166="NÃO","Pendente Fatura", IF(Faturamento!$R166<>"","Aprovado",IF(Faturamento!$O166<>0,"Pendente Emissão","Processo de Calculo")))) -> Aprovado | N54: 767.92 | O54: 575.94 | R54: 575.94 | T54: 62955505067660575,94 | V54: Pago | W54: 575.94 | X54: =IF(Faturamento!$V798="Pago",IFERROR(W54-R54,0),0) -> 0
A55: =VLOOKUP(B55,base!A:M,11,FALSE) -> TRIFÁSICO | B55: 10/5202-7 | C55: 0 | D55: 62955505016160 | E55: energisa_ms | F55: Igreja do Evangelho Quadrangular | G55: 45870 | H55: =Faturamento!$B711&Faturamento!$G711 -> 10/10232-745658 | I55: SIM | J55: 617 | K55: 988.17126 | L55: 825.51519 | M55: =IF(Faturamento!$S711<>"","Não emitido",IF(Faturamento!$I711="NÃO","Pendente Fatura", IF(Faturamento!$R711<>"","Aprovado",IF(Faturamento!$O711<>0,"Pendente Emissão","Processo de Calculo")))) -> Aprovado | N55: 719.84126 | O55: 557.19 | P55: 45910 | Q55: 45920 | R55: 557.19 | T55: 62955505016160557,19 | U55: 09/00012749630-3 | V55: Pago | W55: 557.19 | X55: =IF(Faturamento!$V797="Pago",IFERROR(W55-R55,0),0) -> 0
A56: =VLOOKUP(B56,base!A:M,11,FALSE) -> TRIFÁSICO | B56: 10/2605731-5 | C56: 67992637973 | D56: 62955505017213 | E56: energisa_ms | F56: Igreja do Evangelho Quadrangular | G56: 45748 | H56: =Faturamento!$B376&Faturamento!$G376 -> 10/510330-445870 | I56: SIM | J56: 655 | K56: 1242.25 | L56: 1058.4825 | M56: =IF(Faturamento!$S376<>"","Não emitido",IF(Faturamento!$I376="NÃO","Pendente Fatura", IF(Faturamento!$R376<>"","Aprovado",IF(Faturamento!$O376<>0,"Pendente Emissão","Processo de Calculo")))) -> Aprovado | N56: 735.07 | O56: 551.3 | R56: 551.3 | T56: 62955505017213551,3 | V56: Pago | W56: 551.3 | X56: =IF(Faturamento!$V796="Pago",IFERROR(W56-R56,0),0) -> 0
A57: =VLOOKUP(B57,base!A:M,11,FALSE) -> TRIFÁSICO | B57: 10/1695011-5 | C57: 67991767866 | D57: 62955505461210 | E57: energisa_ms | F57: IGREJA DO EVANGELHO QUADRANGULAR | G57: 45931 | H57: =Faturamento!$B939&Faturamento!$G939 -> 10/237441-145809 | I57: SIM | J57: 659 | K57: 1052.9194 | L57: 827.19326 | M57: Aprovado | N57: 807.0894 | O57: 533.85 | P57: 45967 | Q57: 45974 | R57: 533.85 | T57: =D57&R57 -> 62955505461210533,85 | U57: 09/00013026935-8 | V57: Pago | W57: =R57 -> 533.85 | X57: =IF(Faturamento!$V941="Pago",IFERROR(W57-R57,0),0) -> 0
A58: =VLOOKUP(B58,base!A:M,11,FALSE) -> TRIFÁSICO | B58: 10/2605731-5 | C58: 0 | D58: 62955505017213 | E58: energisa_ms | F58: Igreja do Evangelho Quadrangular | G58: 45870 | H58: =Faturamento!$B713&Faturamento!$G713 -> 10/987178-145931 | I58: SIM | J58: 576 | K58: 868.3776 | L58: 713.53383 | M58: =IF(Faturamento!$S713<>"","Não emitido",IF(Faturamento!$I713="NÃO","Pendente Fatura", IF(Faturamento!$R713<>"","Aprovado",IF(Faturamento!$O713<>0,"Pendente Emissão","Processo de Calculo")))) -> Aprovado | N58: 685.2676 | O58: 530.42 | P58: 45910 | Q58: 45920 | R58: 530.42 | T58: 62955505017213530,42 | U58: 09/00012749633-7 | V58: Pago | W58: 530.42 | X58: =IF(Faturamento!$V795="Pago",IFERROR(W58-R58,0),0) -> 0
A59: =VLOOKUP(B59,base!A:M,11,FALSE) -> TRIFÁSICO | B59: 10/191945-5 | C59: 0 | D59: 62955505215791 | E59: energisa_ms | F59: Igreja do Evangelho Quadrangular | G59: 45901 | H59: =Faturamento!$B810&Faturamento!$G810 -> 10/3214521-145627 | I59: SIM | J59: 599 | K59: 969.7305 | L59: 775.37032 | M59: Aprovado | N59: 723.6605 | O59: 529.3 | P59: 45933 | Q59: 45943 | R59: =O59 -> 529.3 | T59: 62955505215791529,3 | U59: 09/00012851403-9 | V59: Pago | W59: =O59 -> 529.3 | X59: =IF(Faturamento!$V794="Pago",IFERROR(W59-R59,0),0) -> 0
A60: =VLOOKUP(B60,base!A:M,11,FALSE) -> TRIFÁSICO | B60: 10/191945-5 | C60: 67 81355403 | D60: 62955505215791 | E60: energisa_ms | F60: Igreja do Evangelho Quadrangular | G60: 45689 | H60: =Faturamento!$B156&Faturamento!$G156 -> 10/2247256-745717 | I60: SIM | J60: 650 | K60: 1147.2 | L60: 970.925 | M60: =IF(Faturamento!$S156<>"","Não emitido",IF(Faturamento!$I156="NÃO","Pendente Fatura", IF(Faturamento!$R156<>"","Aprovado",IF(Faturamento!$O156<>0,"Pendente Emissão","Processo de Calculo")))) -> Aprovado | N60: 705.1 | O60: 528.83 | R60: 528.83 | T60: 62955505215791528,83 | V60: Pago | W60: 528.83 | X60: =IF(Faturamento!$V793="Pago",IFERROR(W60-R60,0),0) -> 0
A61: =VLOOKUP(B61,base!A:M,11,FALSE) -> TRIFÁSICO | B61: 10/29964-4 | C61: 67996266684 | D61: 62955505067660 | E61: energisa_ms | F61: Igreja do Evangelho Quadrangular | G61: 45717 | H61: =Faturamento!$B243&Faturamento!$G243 -> 10/931327-145658 | I61: SIM | J61: 673 | K61: 798.13 | L61: 622.9775 | M61: =IF(Faturamento!$S243<>"","Não emitido",IF(Faturamento!$I243="NÃO","Pendente Fatura", IF(Faturamento!$R243<>"","Aprovado",IF(Faturamento!$O243<>0,"Pendente Emissão","Processo de Calculo")))) -> Aprovado | N61: 700.61 | O61: 525.46 | R61: 525.46 | T61: 62955505067660525,46 | V61: Pago | W61: 525.46 | X61: =IF(Faturamento!$V792="Pago",IFERROR(W61-R61,0),0) -> 0
A62: =VLOOKUP(B62,base!A:M,11,FALSE) -> TRIFÁSICO | B62: 10/29964-4 | C62: 67996266684 | D62: 62955505067660 | E62: energisa_ms | F62: Igreja do Evangelho Quadrangular | G62: 45748 | H62: =Faturamento!$B340&Faturamento!$G340 -> 10/480529-745748 | I62: SIM | J62: 646 | K62: 776.09 | L62: 607.7825 | M62: =IF(Faturamento!$S340<>"","Não emitido",IF(Faturamento!$I340="NÃO","Pendente Fatura", IF(Faturamento!$R340<>"","Aprovado",IF(Faturamento!$O340<>0,"Pendente Emissão","Processo de Calculo")))) -> Aprovado | N62: 673.23 | O62: 504.92 | R62: 504.92 | T62: 62955505067660504,92 | V62: Pago | W62: 504.92 | X62: =IF(Faturamento!$V791="Pago",IFERROR(W62-R62,0),0) -> 0
A63: =VLOOKUP(B63,base!A:M,11,FALSE) -> BIFÁSICO | B63: 10/61344-8 | C63: 67999998719 | D63: 62955505015431 | E63: energisa_ms | F63: Igreja do Evangelho Quadrangular | G63: 45717 | H63: =Faturamento!$B299&Faturamento!$G299 -> 10/1433087-245717 | I63: SIM | J63: 602 | K63: 1138.57 | L63: 970.5725 | M63: =IF(Faturamento!$S299<>"","Não emitido",IF(Faturamento!$I299="NÃO","Pendente Fatura", IF(Faturamento!$R299<>"","Aprovado",IF(Faturamento!$O299<>0,"Pendente Emissão","Processo de Calculo")))) -> Aprovado | N63: 671.99 | O63: 503.99 | R63: 503.99 | T63: 62955505015431503,99 | V63: Pago | W63: 503.99 | X63: =IF(Faturamento!$V790="Pago",IFERROR(W63-R63,0),0) -> 0
A64: =VLOOKUP(B64,base!A:M,11,FALSE) -> #N/A | B64: 10/2247256-7 | C64: #N/A | D64: #ND | E64: energisa_ms | F64: IGREJA DO EVANGELHO QUADRANGULAR | G64: 45931 | H64: =Faturamento!$B976&Faturamento!$G976 -> 10/505854-045870 | I64: SIM | J64: 629 | M64: Não emitido | N64: 680.30857 | O64: 490.04 | P64: - | Q64: - | R64: - | S64: Pendente dado cadastral | T64: =D64&R64 -> #ND- | U64: #N/A | V64: Não faturado | X64: =IF(Faturamento!$V978="Pago",IFERROR(W64-R64,0),0) -> 0
A65: =VLOOKUP(B65,base!A:M,11,FALSE) -> TRIFÁSICO | B65: 10/2599101-9 | C65: 67991120875 | D65: 62955505379395 | E65: energisa_ms | F65: Igreja do Evangelho Quadrangular | G65: 45778 | H65: =Faturamento!$B470&Faturamento!$G470 -> 10/63920-345809 | I65: SIM | J65: 575 | K65: 759.3825 | L65: 597.66437 | M65: =IF(Faturamento!$S470<>"","Não emitido",IF(Faturamento!$I470="NÃO","Pendente Fatura", IF(Faturamento!$R470<>"","Aprovado",IF(Faturamento!$O470<>0,"Pendente Emissão","Processo de Calculo")))) -> Aprovado | N65: 646.8725 | O65: 485.15 | R65: 485.15 | T65: 62955505379395485,15 | V65: Atrasado | W65: 0 | X65: =IF(Faturamento!$V184="Pago",IFERROR(W65-R65,0),0) -> -485.15 | Z65: Cobrança Regular
A66: =VLOOKUP(B66,base!A:M,11,FALSE) -> TRIFÁSICO | B66: 10/513413-5 | C66: 67992637973 | D66: 62955505321630 | E66: energisa_ms | F66: IGREJA DO EVANGELHO QUADRANGULAR | G66: 45931 | H66: =Faturamento!$B944&Faturamento!$G944 -> 10/987178-145809 | I66: SIM | J66: 545 | K66: 917.941 | L66: 730.16968 | M66: Aprovado | N66: 671.381 | O66: 483.61 | P66: 45967 | Q66: 45974 | R66: 483.61 | T66: =D66&R66 -> 62955505321630483,61 | U66: 09/00013026943-2 | V66: Pago | W66: =R66 -> 483.61 | X66: =IF(Faturamento!$V946="Pago",IFERROR(W66-R66,0),0) -> 0
A67: =VLOOKUP(B67,base!A:M,11,FALSE) -> TRIFÁSICO | B67: 10/202838-9 | C67: 0 | D67: 62955505016403 | E67: energisa_ms | F67: Igreja do Evangelho Quadrangular | G67: 45901 | H67: =Faturamento!$B806&Faturamento!$G806 -> 10/29964-445627 | I67: SIM | J67: 540 | K67: 904.206 | L67: 729.0021 | M67: Aprovado | N67: 652.336 | O67: 477.13 | P67: 45933 | Q67: 45943 | R67: =O67 -> 477.13 | T67: 62955505016403477,13 | U67: 09/00012851399-9 | V67: Pago | W67: =O67 -> 477.13 | X67: =IF(Faturamento!$V789="Pago",IFERROR(W67-R67,0),0) -> 0
A68: =VLOOKUP(B68,base!A:M,11,FALSE) -> TRIFÁSICO | B68: 10/510330-4 | C68: 67992637973 | D68: 62955505367117 | E68: energisa_ms | F68: Igreja do Evangelho Quadrangular | G68: 45689 | H68: =Faturamento!$B174&Faturamento!$G174 -> 10/1695011-545717 | I68: SIM | J68: 606 | K68: 889.87 | L68: 732.4525 | M68: =IF(Faturamento!$S174<>"","Não emitido",IF(Faturamento!$I174="NÃO","Pendente Fatura", IF(Faturamento!$R174<>"","Aprovado",IF(Faturamento!$O174<>0,"Pendente Emissão","Processo de Calculo")))) -> Aprovado | N68: 629.67 | O68: 472.25 | R68: 472.25 | T68: 62955505367117472,25 | V68: Pago | W68: 472.25 | X68: =IF(Faturamento!$V788="Pago",IFERROR(W68-R68,0),0) -> 0
A69: =VLOOKUP(B69,base!A:M,11,FALSE) -> TRIFÁSICO | B69: 10/3030784-7 | C69: 67996266684 | D69: 62955505016080 | E69: energisa_ms | F69: Igreja do Evangelho Quadrangular | G69: 45689 | H69: =Faturamento!$B168&Faturamento!$G168 -> 10/3092868-345748 | I69: SIM | J69: 583 | K69: 822.51 | L69: 667.21 | M69: =IF(Faturamento!$S168<>"","Não emitido",IF(Faturamento!$I168="NÃO","Pendente Fatura", IF(Faturamento!$R168<>"","Aprovado",IF(Faturamento!$O168<>0,"Pendente Emissão","Processo de Calculo")))) -> Aprovado | N69: 621.2 | O69: 465.9 | R69: 465.9 | T69: 62955505016080465,9 | V69: Pago | W69: 465.9 | X69: =IF(Faturamento!$V787="Pago",IFERROR(W69-R69,0),0) -> 0
A70: =VLOOKUP(B70,base!A:M,11,FALSE) -> TRIFÁSICO | B70: 10/276283-9 | C70: 46 999066691 | D70: 62955505177504 | E70: energisa_ms | F70: Igreja do Evangelho Quadrangular | G70: 45658 | H70: =Faturamento!$B68&Faturamento!$G68 -> 10/510330-445689 | I70: SIM | J70: 589 | K70: 836.99 | L70: 683.3425 | M70: =IF(Faturamento!$S68<>"","Não emitido",IF(Faturamento!$I68="NÃO","Pendente Fatura", IF(Faturamento!$R68<>"","Aprovado",IF(Faturamento!$O68<>0,"Pendente Emissão","Processo de Calculo")))) -> Aprovado | N70: 614.59 | O70: 460.94 | R70: 460.94 | T70: 62955505177504460,94 | V70: Pago | W70: 460.94 | X70: =IF(Faturamento!$V786="Pago",IFERROR(W70-R70,0),0) -> 0
A71: =VLOOKUP(B71,base!A:M,11,FALSE) -> TRIFÁSICO | B71: 10/29964-4 | C71: 67996266684 | D71: 62955505067660 | E71: energisa_ms | F71: Igreja do Evangelho Quadrangular | G71: 45658 | H71: =Faturamento!$B69&Faturamento!$G69 -> 10/3030784-745689 | I71: SIM | J71: 547 | K71: 876.26 | L71: 723.615 | M71: =IF(Faturamento!$S69<>"","Não emitido",IF(Faturamento!$I69="NÃO","Pendente Fatura", IF(Faturamento!$R69<>"","Aprovado",IF(Faturamento!$O69<>0,"Pendente Emissão","Processo de Calculo")))) -> Aprovado | N71: 610.58 | O71: 457.94 | R71: 457.94 | T71: 62955505067660457,94 | V71: Pago | W71: 457.94 | X71: =IF(Faturamento!$V785="Pago",IFERROR(W71-R71,0),0) -> 0
A72: =VLOOKUP(B72,base!A:M,11,FALSE) -> TRIFÁSICO | B72: 10/127464-6 | C72: 67996150274 | D72: 62955505331198 | E72: energisa_ms | F72: IGREJA DO EVANGELHO QUADRANGULAR | G72: 45931 | H72: =Faturamento!$B897&Faturamento!$G897 -> 10/127464-645717 | I72: SIM | J72: 576 | K72: 826.118 | L72: 652.25876 | M72: Aprovado | N72: 621.638 | O72: 447.78 | P72: 45967 | Q72: 45974 | R72: 447.78 | T72: =D72&R72 -> 62955505331198447,78 | U72: 09/00013026871-5 | V72: Pago | W72: =R72 -> 447.78 | X72: =IF(Faturamento!$V899="Pago",IFERROR(W72-R72,0),0) -> 0
A73: =VLOOKUP(B73,base!A:M,11,FALSE) -> TRIFÁSICO | B73: 10/3092868-3 | C73: 67 91285460 | D73: 62955505419443 | E73: energisa_ms | F73: Igreja do Evangelho Quadrangular | G73: 45717 | H73: =Faturamento!$B248&Faturamento!$G248 -> 10/61344-845931 | I73: SIM | J73: 568 | K73: 690.96 | L73: 543.3 | M73: =IF(Faturamento!$S248<>"","Não emitido",IF(Faturamento!$I248="NÃO","Pendente Fatura", IF(Faturamento!$R248<>"","Aprovado",IF(Faturamento!$O248<>0,"Pendente Emissão","Processo de Calculo")))) -> Aprovado | N73: 590.64 | O73: 442.98 | R73: 442.98 | T73: 62955505419443442,98 | V73: Pago | W73: 442.98 | X73: =IF(Faturamento!$V784="Pago",IFERROR(W73-R73,0),0) -> 0
A74: =VLOOKUP(B74,base!A:M,11,FALSE) -> #N/A | B74: 10/925970-6 | C74: #N/A | D74: 62955505057789 | E74: energisa_ms | F74: Igreja do Evangelho Quadrangular | G74: 45717 | H74: =Faturamento!$B284&Faturamento!$G284 -> 10/2599101-945870 | I74: SIM | J74: 602 | K74: 1109.56 | L74: 962.9625 | M74: =IF(Faturamento!$S284<>"","Não emitido",IF(Faturamento!$I284="NÃO","Pendente Fatura", IF(Faturamento!$R284<>"","Aprovado",IF(Faturamento!$O284<>0,"Pendente Emissão","Processo de Calculo")))) -> Aprovado | N74: 586.39 | O74: 439.79 | R74: 439.79 | T74: 62955505057789439,79 | V74: Atrasado | W74: 0 | X74: =IF(Faturamento!$V112="Pago",IFERROR(W74-R74,0),0) -> -439.79 | Z74: Cobrança Regular | AI74: =VLOOKUP(B74,'[1]Conciliação - 032025'!$A:$L,12,FALSE) -> VALOR DEVIDO - Cancelamento via email dia 30/04, tenho tudo formalizado por whatsapp com Diil
A75: =VLOOKUP(B75,base!A:M,11,FALSE) -> TRIFÁSICO | B75: 10/202838-9 | C75: 67992637973 | D75: 62955505016403 | E75: energisa_ms | F75: Igreja do Evangelho Quadrangular | G75: 45748 | H75: =Faturamento!$B374&Faturamento!$G374 -> 10/1672452-845809 | I75: SIM | J75: 523 | K75: 1079.03 | L75: 933.07 | M75: =IF(Faturamento!$S374<>"","Não emitido",IF(Faturamento!$I374="NÃO","Pendente Fatura", IF(Faturamento!$R374<>"","Aprovado",IF(Faturamento!$O374<>0,"Pendente Emissão","Processo de Calculo")))) -> Aprovado | N75: 583.84 | O75: 437.88 | R75: 437.88 | T75: 62955505016403437,88 | V75: Pago | W75: 437.88 | X75: =IF(Faturamento!$V783="Pago",IFERROR(W75-R75,0),0) -> 0
A76: =VLOOKUP(B76,base!A:M,11,FALSE) -> TRIFÁSICO | B76: 10/1672452-8 | C76: 67992637973 | D76: 62955505017213 | E76: energisa_ms | F76: IGREJA DO EVANGELHO QUADRANGULAR | G76: 45931 | H76: =Faturamento!$B951&Faturamento!$G951 -> 10/505854-045809 | I76: SIM | J76: 487 | K76: 785.0519 | L76: 618.63663 | M76: Aprovado | N76: 595.0219 | O76: 428.75 | P76: 45967 | Q76: 45974 | R76: 428.75 | T76: =D76&R76 -> 62955505017213428,75 | U76: 09/00013026954-9 | V76: Pago | W76: =R76 -> 428.75 | X76: =IF(Faturamento!$V953="Pago",IFERROR(W76-R76,0),0) -> 0
A77: =VLOOKUP(B77,base!A:M,11,FALSE) -> #N/A | B77: 10/2247256-7 | C77: #N/A | D77: 62955505015199 | E77: energisa_ms | F77: Igreja do Evangelho Quadrangular | G77: 45658 | H77: =Faturamento!$B101&Faturamento!$G101 -> 10/925970-645931 | I77: SIM | J77: 576 | K77: 821.29 | L77: 678.6175 | M77: Aprovado | N77: 570.69 | O77: 428.02 | R77: 428.02 | T77: 62955505015199428,02 | V77: Atrasado | W77: 0 | X77: =IF(Faturamento!$V53="Pago",IFERROR(W77-R77,0),0) -> -428.02 | Z77: Cobrança Regular
A78: =VLOOKUP(B78,base!A:M,11,FALSE) -> TRIFÁSICO | B78: 10/3030784-7 | C78: 67996266684 | D78: 62955505016080 | E78: energisa_ms | F78: Igreja do Evangelho Quadrangular | G78: 45717 | H78: =Faturamento!$B247&Faturamento!$G247 -> 10/3040565-845870 | I78: SIM | J78: 548 | K78: 746.1 | L78: 603.6275 | M78: =IF(Faturamento!$S247<>"","Não emitido",IF(Faturamento!$I247="NÃO","Pendente Fatura", IF(Faturamento!$R247<>"","Aprovado",IF(Faturamento!$O247<>0,"Pendente Emissão","Processo de Calculo")))) -> Aprovado | N78: 569.89 | O78: 427.42 | R78: 427.42 | T78: 62955505016080427,42 | V78: Pago | W78: 427.42 | X78: =IF(Faturamento!$V782="Pago",IFERROR(W78-R78,0),0) -> 0
A79: =VLOOKUP(B79,base!A:M,11,FALSE) -> BIFÁSICO | B79: 10/1081489-5 | C79: =VLOOKUP(B79,Base_Clientes[[INSTALAÇÃO]:[TELEFONE]],10,0) -> 67996446178 | D79: 62955505016918 | E79: energisa_ms | F79: Igreja do Evangelho Quadrangular | G79: 45901 | H79: =Faturamento!$B847&Faturamento!$G847 -> 10/504844-245689 | I79: SIM | J79: 386 | K79: 467.83 | L79: 369.16205 | M79: Aprovado | N79: 367.37 | O79: 268.7 | P79: 45933 | Q79: 45943 | R79: =O79 -> 268.7 | T79: 62955505016918268,7 | U79: 09/00012851434-4 | V79: Atrasado | X79: =IF(Faturamento!$V883="Pago",IFERROR(W79-R79,0),0) -> 0 | Z79: Cobrança Regular
A80: =VLOOKUP(B80,base!A:M,11,FALSE) -> TRIFÁSICO | B80: 10/15297-5 | C80: 67996266684 | D80: 62955505312487 | E80: energisa_ms | F80: IGREJA DO EVANGELHO QUADRANGULAR | G80: 45931 | H80: =Faturamento!$B898&Faturamento!$G898 -> 10/24514-245717 | I80: SIM | J80: 555 | K80: 687.2075 | L80: 522.09677 | M80: Aprovado | N80: 590.3575 | O80: 425.25 | P80: 45967 | Q80: 45974 | R80: 425.25 | T80: =D80&R80 -> 62955505312487425,25 | U80: 09/00013026873-1 | V80: Pago | W80: =R80 -> 425.25 | X80: =IF(Faturamento!$V900="Pago",IFERROR(W80-R80,0),0) -> 0
A81: =VLOOKUP(B81,base!A:M,11,FALSE) -> TRIFÁSICO | B81: 10/1674177-9 | C81: 6784548587 | D81: 62955505016160 | E81: energisa_ms | F81: IGREJA DO EVANGELHO QUADRANGULAR | G81: 45931 | H81: =Faturamento!$B902&Faturamento!$G902 -> 10/41548-945717 | I81: SIM | J81: 873 | K81: 1120.88 | L81: 881.30677 | M81: Aprovado | N81: 856.6 | O81: 424.53 | P81: 45967 | Q81: 45974 | R81: 424.53 | T81: =D81&R81 -> 62955505016160424,53 | U81: 09/00013026879-8 | V81: Pago | W81: =R81 -> 424.53 | X81: =IF(Faturamento!$V904="Pago",IFERROR(W81-R81,0),0) -> 0
A82: =VLOOKUP(B82,base!A:M,11,FALSE) -> BIFÁSICO | B82: 10/1939035-0 | C82: 67 91285460 | D82: 62955505419443 | E82: energisa_ms | F82: Igreja do Evangelho Quadrangular | G82: 45717 | H82: =Faturamento!$B278&Faturamento!$G278 -> 10/1695011-545658 | I82: SIM | J82: 543 | K82: 657.72 | L82: 516.68 | M82: =IF(Faturamento!$S278<>"","Não emitido",IF(Faturamento!$I278="NÃO","Pendente Fatura", IF(Faturamento!$R278<>"","Aprovado",IF(Faturamento!$O278<>0,"Pendente Emissão","Processo de Calculo")))) -> Aprovado | N82: 564.16 | O82: 423.12 | R82: 423.12 | T82: 62955505419443423,12 | V82: Pago | W82: 423.12 | X82: =IF(Faturamento!$V781="Pago",IFERROR(W82-R82,0),0) -> 0
A83: =VLOOKUP(B83,base!A:M,11,FALSE) -> TRIFÁSICO | B83: 10/510330-4 | C83: 67992637973 | D83: 62955505367117 | E83: energisa_ms | F83: Igreja do Evangelho Quadrangular | G83: 45717 | H83: =Faturamento!$B246&Faturamento!$G246 -> 10/1081489-545778 | I83: SIM | J83: 542 | K83: 1025.94 | L83: 884.96 | M83: =IF(Faturamento!$S246<>"","Não emitido",IF(Faturamento!$I246="NÃO","Pendente Fatura", IF(Faturamento!$R246<>"","Aprovado",IF(Faturamento!$O246<>0,"Pendente Emissão","Processo de Calculo")))) -> Aprovado | N83: 563.92 | O83: 422.94 | R83: 422.94 | T83: 62955505367117422,94 | V83: Pago | W83: 422.94 | X83: =IF(Faturamento!$V780="Pago",IFERROR(W83-R83,0),0) -> 0
A84: =VLOOKUP(B84,base!A:M,11,FALSE) -> TRIFÁSICO | B84: 10/5202-7 | C84: 67 996469842 | D84: 62955505393207 | E84: energisa_ms | F84: Igreja do Evangelho Quadrangular | G84: 45839 | H84: =Faturamento!$B618&Faturamento!$G618 -> 10/501586-245870 | I84: SIM | J84: 459 | K84: 759.2133 | L84: 636.74506 | M84: =IF(Faturamento!$S618<>"","Não emitido",IF(Faturamento!$I618="NÃO","Pendente Fatura", IF(Faturamento!$R618<>"","Aprovado",IF(Faturamento!$O618<>0,"Pendente Emissão","Processo de Calculo")))) -> Aprovado | N84: 545.3533 | O84: 422.89 | P84: 45910 | Q84: 45920 | R84: 422.89 | T84: 62955505393207422,89 | U84: 09/00012683467-8 | V84: Pago | W84: 422.89 | X84: =IF(Faturamento!$V779="Pago",IFERROR(W84-R84,0),0) -> 0
A85: =VLOOKUP(B85,base!A:M,11,FALSE) -> #N/A | B85: 10/3005226-0 | C85: #N/A | D85: #ND | E85: energisa_ms | F85: IGREJA DO EVANGELHO QUADRANGULAR | G85: 45931 | H85: =Faturamento!$B979&Faturamento!$G979 -> 10/452884-045901 | I85: SIM | J85: 317 | M85: Não emitido | N85: 505.47 | O85: 418.48 | P85: - | Q85: - | R85: - | S85: Pendente dado cadastral | T85: =D85&R85 -> #ND- | U85: #N/A | V85: Não faturado | X85: =IF(Faturamento!$V981="Pago",IFERROR(W85-R85,0),0) -> 0
A86: =VLOOKUP(B86,base!A:M,11,FALSE) -> TRIFÁSICO | B86: 10/15297-5 | C86: 0 | D86: 62955505312487 | E86: energisa_ms | F86: Igreja do Evangelho Quadrangular | G86: 45901 | H86: =Faturamento!$B850&Faturamento!$G850 -> 10/480529-745689 | I86: SIM | J86: 539 | K86: 665.96 | L86: 513.70512 | M86: Aprovado | N86: 566.89 | O86: 414.64 | P86: 45933 | Q86: 45943 | R86: =O86 -> 414.64 | T86: 62955505312487414,64 | U86: 09/00012851437-7 | V86: Pago | W86: =O86 -> 414.64 | X86: =IF(Faturamento!$V778="Pago",IFERROR(W86-R86,0),0) -> 0
A87: =VLOOKUP(B87,base!A:M,11,FALSE) -> TRIFÁSICO | B87: 10/2599101-9 | C87: 67991120875 | D87: 62955505379395 | E87: energisa_ms | F87: Igreja do Evangelho Quadrangular | G87: 45658 | H87: =Faturamento!$B66&Faturamento!$G66 -> 10/513413-545931 | I87: SIM | J87: 493 | K87: 851.71 | L87: 714.1325 | M87: =IF(Faturamento!$S66<>"","Não emitido",IF(Faturamento!$I66="NÃO","Pendente Fatura", IF(Faturamento!$R66<>"","Aprovado",IF(Faturamento!$O66<>0,"Pendente Emissão","Processo de Calculo")))) -> Aprovado | N87: 550.31 | O87: 412.73 | R87: 412.73 | T87: 62955505379395412,73 | V87: Pago | W87: 412.73 | X87: =IF(Faturamento!$V777="Pago",IFERROR(W87-R87,0),0) -> 0 | AA87: 283032 | AB87: 502 | AC87: Igreja do Evangelho Quadrangular | AD87: '62955505015512' | AE87: 59.21 | AG87: A Unidade Consumidora 10/466560-0 economizou R$19,74 na fatura referente à jun/2025 consumindo 79 kWh em créditos de energia renovável conforme fatura de energia. A economia foi de 25% em relação ao que seria pago para a Energisa considerando os créditos consumidos. Atenção: Mantenha as contas da Energisa em dia para evitar cortes. | AH87: monicadossantosfonseca@hotmail.com
A88: =VLOOKUP(B88,base!A:M,11,FALSE) -> TRIFÁSICO | B88: 10/2605731-5 | C88: 67992637973 | D88: 62955505017213 | E88: energisa_ms | F88: Igreja do Evangelho Quadrangular | G88: 45839 | H88: =Faturamento!$B620&Faturamento!$G620 -> 10/24514-245870 | I88: SIM | J88: 450 | K88: 701.395 | L88: 581.3236 | M88: =IF(Faturamento!$S620<>"","Não emitido",IF(Faturamento!$I620="NÃO","Pendente Fatura", IF(Faturamento!$R620<>"","Aprovado",IF(Faturamento!$O620<>0,"Pendente Emissão","Processo de Calculo")))) -> Aprovado | N88: 529.685 | O88: 409.61 | P88: 45910 | Q88: 45920 | R88: 409.61 | T88: 62955505017213409,61 | U88: 09/00012683469-4 | V88: Pago | W88: 409.61 | X88: =IF(Faturamento!$V776="Pago",IFERROR(W88-R88,0),0) -> 0
A89: =VLOOKUP(B89,base!A:M,11,FALSE) -> TRIFÁSICO | B89: 10/1035655-8 | C89: 67996135721 | D89: 62955505182257 | E89: energisa_ms | F89: Igreja do Evangelho Quadrangular | G89: 45717 | H89: =Faturamento!$B251&Faturamento!$G251 -> 10/109074-545870 | I89: SIM | J89: 481 | K89: 727.21 | L89: 592.98 | M89: =IF(Faturamento!$S251<>"","Não emitido",IF(Faturamento!$I251="NÃO","Pendente Fatura", IF(Faturamento!$R251<>"","Aprovado",IF(Faturamento!$O251<>0,"Pendente Emissão","Processo de Calculo")))) -> Aprovado | N89: 536.92 | O89: 402.69 | R89: 402.69 | T89: 62955505182257402,69 | V89: Pago | W89: 402.69 | X89: =IF(Faturamento!$V775="Pago",IFERROR(W89-R89,0),0) -> 0 | AI89: =VLOOKUP(B89,'[1]Conciliação - 032025'!$A:$L,12,FALSE) -> DEPÓSITO UNIFICADO ITAU R$1.310,17 - 10/06/2025
A90: =VLOOKUP(B90,base!A:M,11,FALSE) -> TRIFÁSICO | B90: 10/2605731-5 | C90: 67992637973 | D90: 62955505017213 | E90: energisa_ms | F90: Igreja do Evangelho Quadrangular | G90: 45778 | H90: =Faturamento!$B473&Faturamento!$G473 -> 10/76927-345809 | I90: SIM | J90: 466 | K90: 964.0413 | L90: 831.00597 | M90: =IF(Faturamento!$S473<>"","Não emitido",IF(Faturamento!$I473="NÃO","Pendente Fatura", IF(Faturamento!$R473<>"","Aprovado",IF(Faturamento!$O473<>0,"Pendente Emissão","Processo de Calculo")))) -> Aprovado | N90: 532.1413 | O90: 399.11 | R90: 399.11 | T90: 62955505017213399,11 | V90: Pago | W90: 399.11 | X90: =IF(Faturamento!$V774="Pago",IFERROR(W90-R90,0),0) -> 0
A91: =VLOOKUP(B91,base!A:M,11,FALSE) -> TRIFÁSICO | B91: 10/81222-2 | C91: 67 992491551 | D91: 62955505015946 | E91: energisa_ms | F91: IGREJA DO EVANGELHO QUADRANGULAR | G91: 45931 | H91: =Faturamento!$B911&Faturamento!$G911 -> 10/2344751-945717 | I91: SIM | J91: 589 | K91: 775.285 | L91: 599.64504 | M91: Aprovado | N91: 628.005 | O91: 398.21 | P91: 45967 | Q91: 45974 | R91: 398.21 | T91: =D91&R91 -> 62955505015946398,21 | U91: 09/00013026893-9 | V91: Pago | W91: =R91 -> 398.21 | X91: =IF(Faturamento!$V913="Pago",IFERROR(W91-R91,0),0) -> 0
A92: =VLOOKUP(B92,base!A:M,11,FALSE) -> TRIFÁSICO | B92: 10/15297-5 | C92: 67996266684 | D92: 62955505312487 | E92: energisa_ms | F92: Igreja do Evangelho Quadrangular | G92: 45778 | H92: =Faturamento!$B484&Faturamento!$G484 -> 10/3123706-845778 | I92: SIM | J92: 540 | K92: 553.35 | L92: 421.495 | M92: =IF(Faturamento!$S484<>"","Não emitido",IF(Faturamento!$I484="NÃO","Pendente Fatura", IF(Faturamento!$R484<>"","Aprovado",IF(Faturamento!$O484<>0,"Pendente Emissão","Processo de Calculo")))) -> Aprovado | N92: 527.42 | O92: 395.57 | R92: 395.57 | T92: 62955505312487395,57 | V92: Pago | W92: 395.57 | X92: =IF(Faturamento!$V773="Pago",IFERROR(W92-R92,0),0) -> 0
A93: =VLOOKUP(B93,base!A:M,11,FALSE) -> TRIFÁSICO | B93: 10/1672452-8 | C93: 67992637973 | D93: 62955505017213 | E93: energisa_ms | F93: Igreja do Evangelho Quadrangular | G93: 45689 | H93: =Faturamento!$B152&Faturamento!$G152 -> 10/276283-945689 | I93: SIM | J93: 464 | K93: 696.99 | L93: 567.505 | M93: =IF(Faturamento!$S152<>"","Não emitido",IF(Faturamento!$I152="NÃO","Pendente Fatura", IF(Faturamento!$R152<>"","Aprovado",IF(Faturamento!$O152<>0,"Pendente Emissão","Processo de Calculo")))) -> Aprovado | N93: 517.94 | O93: 388.46 | R93: 388.46 | T93: 62955505017213388,46 | V93: Pago | W93: 388.46 | X93: =IF(Faturamento!$V772="Pago",IFERROR(W93-R93,0),0) -> 0
A94: =VLOOKUP(B94,base!A:M,11,FALSE) -> TRIFÁSICO | B94: 10/532081-7 | C94: 67 992321318 | D94: 62955505193534 | E94: energisa_ms | F94: Igreja do Evangelho Quadrangular | G94: 45689 | H94: =Faturamento!$B178&Faturamento!$G178 -> 10/260761-245748 | I94: SIM | J94: 476 | K94: 739.42 | L94: 611.065 | M94: =IF(Faturamento!$S178<>"","Não emitido",IF(Faturamento!$I178="NÃO","Pendente Fatura", IF(Faturamento!$R178<>"","Aprovado",IF(Faturamento!$O178<>0,"Pendente Emissão","Processo de Calculo")))) -> Aprovado | N94: 513.42 | O94: 385.07 | R94: 385.07 | T94: 62955505193534385,07 | V94: Pago | W94: 385.07 | X94: =IF(Faturamento!$V771="Pago",IFERROR(W94-R94,0),0) -> 0
A95: =VLOOKUP(B95,base!A:M,11,FALSE) -> TRIFÁSICO | B95: 10/202838-9 | C95: 0 | D95: 62955505016403 | E95: energisa_ms | F95: Igreja do Evangelho Quadrangular | G95: 45870 | H95: =Faturamento!$B717&Faturamento!$G717 -> 10/52987-545809 | I95: SIM | J95: 420 | K95: 744.866 | L95: 632.8422 | M95: =IF(Faturamento!$S717<>"","Não emitido",IF(Faturamento!$I717="NÃO","Pendente Fatura", IF(Faturamento!$R717<>"","Aprovado",IF(Faturamento!$O717<>0,"Pendente Emissão","Processo de Calculo")))) -> Aprovado | N95: 495.766 | O95: 383.74 | P95: 45910 | Q95: 45920 | R95: 383.74 | T95: 62955505016403383,74 | U95: 09/00012749637-8 | V95: Pago | W95: 383.74 | X95: =IF(Faturamento!$V770="Pago",IFERROR(W95-R95,0),0) -> 0
A96: =VLOOKUP(B96,base!A:M,11,FALSE) -> TRIFÁSICO | B96: 10/1695011-5 | C96: 0 | D96: 62955505461210 | E96: energisa_ms | F96: Igreja do Evangelho Quadrangular | G96: 45870 | H96: =Faturamento!$B715&Faturamento!$G715 -> 10/69319-245839 | I96: SIM | J96: 418 | K96: 698.19417 | L96: 587.68472 | M96: =IF(Faturamento!$S715<>"","Não emitido",IF(Faturamento!$I715="NÃO","Pendente Fatura", IF(Faturamento!$R715<>"","Aprovado",IF(Faturamento!$O715<>0,"Pendente Emissão","Processo de Calculo")))) -> Aprovado | N96: 489.06417 | O96: 378.55 | P96: 45910 | Q96: 45920 | R96: 378.55 | T96: 62955505461210378,55 | U96: 09/00012749635-2 | V96: Pago | W96: 378.55 | X96: =IF(Faturamento!$V769="Pago",IFERROR(W96-R96,0),0) -> 0
A97: =VLOOKUP(B97,base!A:M,11,FALSE) -> TRIFÁSICO | B97: 10/1035655-8 | C97: 67996135721 | D97: 62955505182257 | E97: energisa_ms | F97: Igreja do Evangelho Quadrangular | G97: 45658 | H97: =Faturamento!$B46&Faturamento!$G46 -> 10/2599101-945689 | I97: SIM | J97: 497 | K97: 686.02 | L97: 559.8875 | M97: =IF(Faturamento!$S46<>"","Não emitido",IF(Faturamento!$I46="NÃO","Pendente Fatura", IF(Faturamento!$R46<>"","Aprovado",IF(Faturamento!$O46<>0,"Pendente Emissão","Processo de Calculo")))) -> Aprovado | N97: 504.53 | O97: 378.4 | R97: 378.4 | T97: 62955505182257378,4 | V97: Pago | W97: 378.4 | X97: =IF(Faturamento!$V768="Pago",IFERROR(W97-R97,0),0) -> 0 | AA97: 283032 | AB97: 502 | AC97: Igreja do Evangelho Quadrangular | AD97: '62955505015946' | AE97: 182.75 | AG97: A Unidade Consumidora 10/81222-2 economizou R$60,92 na fatura referente à jun/2025 consumindo 241 kWh em créditos de energia renovável conforme fatura de energia. A economia foi de 25% em relação ao que seria pago para a Energisa considerando os créditos consumidos. Atenção: Mantenha as contas da Energisa em dia para evitar cortes. | AH97: ieqreg349cassi@gmail.com
A98: =VLOOKUP(B98,base!A:M,11,FALSE) -> TRIFÁSICO | B98: 10/8777-5 | C98: Solicitação de distrato | D98: 62955505122432 | E98: energisa_ms | F98: Igreja do Evangelho Quadrangular | G98: 45870 | H98: =Faturamento!$B762&Faturamento!$G762 -> 10/987178-145748 | I98: SIM | J98: 477 | K98: 675.35857 | L98: 565.28198 | M98: =IF(Faturamento!$S762<>"","Não emitido",IF(Faturamento!$I762="NÃO","Pendente Fatura", IF(Faturamento!$R762<>"","Aprovado",IF(Faturamento!$O762<>0,"Pendente Emissão","Processo de Calculo")))) -> Aprovado | N98: 487.14857 | O98: 377.07 | P98: 45910 | Q98: 45920 | R98: 377.07 | T98: 62955505122432377,07 | U98: 09/00012749677-4 | V98: Pago | W98: 377.07 | X98: =IF(Faturamento!$V767="Pago",IFERROR(W98-R98,0),0) -> 0
A99: =VLOOKUP(B99,base!A:M,11,FALSE) -> #N/A | B99: 10/925970-6 | C99: #N/A | D99: 62955505057789 | E99: energisa_ms | F99: Igreja do Evangelho Quadrangular | G99: 45748 | H99: =Faturamento!$B381&Faturamento!$G381 -> 10/931327-145839 | I99: SIM | J99: 517 | K99: 706.59 | L99: 580.905 | M99: =IF(Faturamento!$S381<>"","Não emitido",IF(Faturamento!$I381="NÃO","Pendente Fatura", IF(Faturamento!$R381<>"","Aprovado",IF(Faturamento!$O381<>0,"Pendente Emissão","Processo de Calculo")))) -> Aprovado | N99: 502.74 | O99: 377.05 | R99: 377.05 | T99: 62955505057789377,05 | V99: Pago | W99: 377.05 | X99: =IF(Faturamento!$V766="Pago",IFERROR(W99-R99,0),0) -> 0
A100: =VLOOKUP(B100,base!A:M,11,FALSE) -> BIFÁSICO | B100: 10/61344-8 | C100: 67999998719 | D100: 62955505015431 | E100: energisa_ms | F100: Igreja do Evangelho Quadrangular | G100: 45748 | H100: =Faturamento!$B396&Faturamento!$G396 -> 10/260761-245901 | I100: SIM | J100: 517 | K100: 923.67 | L100: 798.045 | M100: =IF(Faturamento!$S396<>"","Não emitido",IF(Faturamento!$I396="NÃO","Pendente Fatura", IF(Faturamento!$R396<>"","Aprovado",IF(Faturamento!$O396<>0,"Pendente Emissão","Processo de Calculo")))) -> Aprovado | N100: 502.5 | O100: 376.88 | R100: 376.88 | T100: 62955505015431376,88 | V100: Pago | W100: 376.88 | X100: =IF(Faturamento!$V765="Pago",IFERROR(W100-R100,0),0) -> 0
...

Sheet Acordos
A1: Instalação | B1: Valor total | C1: Referência Negociadas | D1: Data de Pagamento | E1: Forma de Pagamento | F1: Status | G1: Verificação extrato | H1: Responsável Verificação
A2: 10/175073-6 | B2: 117.9 | C2: Jan/25, Fev/25, Mar/25, Abr/25 e Mai/25 | D2: 45888 | E2: Pix | F2: Quitado | G2: ok | H2: Carol
A3: 10/987178-1 | B3: 10.88 | C3: 45748 | D3: 45895 | E3: Pix | F3: Quitado | G3: ok | H3: Carol
A4: 10/3123706-8 | B4: 266.72 | C4: Abr/25 e Maio/25 | D4: 45897 | E4: Pix | F4: Quitado | G4: ok | H4: Carol
A5: 10/113971-6 | B5: 86.94 | C5: 45839 | D5: 45897 | E5: Pix | F5: Quitado | G5: ok | H5: Carol
A6: 10/530195-7 | B6: 239.06 | C6: Jan/25, Abr/25, Mai/25 e Jun/25 | D6: 1ª Parc. Dia 04/09 - Pago (Valor R$ 119,53) 2ª Parc. Dia 25/09 - Pago (Valor R$ 119,53) | E6: Pix | F6: Quitado | G6: ok | H6: Carol
A7: 10/341308-5 | B7: 203.23 | C7: 45778 | D7: 45901 | E7: Pix | F7: Quitado | G7: ok | H7: Carol
A8: 10/1117293-9 | B8: 293.26 | C8: Jan/25, Abr/25, Mai/25, Jun/25 e Jul/25 | D8: 45901 | E8: Pix | F8: Quitado | G8: ok | H8: Carol
A9: 10/3125732-2 | B9: 104.66 | C9: 45839 | D9: 45901 | E9: Pix | F9: Quitado | G9: ok | H9: Carol
A10: 10/78338-1 | B10: 176.78 | C10: 45778 | D10: 45901 | E10: Pix | F10: Quitado | G10: ok | H10: Carol
A11: 10/3139326-7 | B11: 321.21 | C11: 45839 | D11: 45901 | E11: Pix | F11: Quitado | G11: ok | H11: Carol
A12: 10/142353-2 | B12: 282.64 | C12: 45839 | D12: 45901 | E12: Pix | F12: Quitado | G12: ok | H12: Carol
A13: 10/76927-3 | B13: 71.45 | C13: 45839 | D13: 45904 | E13: Pix | F13: Quitado | G13: ok | H13: Carol
A14: 10/175073-6 | B14: 149.22 | C14: Pagamento em Duplicidade (Fev/25 à Maio/25 - Sem desconto) | D14: 45904 | E14: Pix | F14: Quitado | G14: ok | H14: Carol
A15: 10/3123706-8 | B15: 238.05 | C15: 45839 | D15: 45904 | E15: Pix | F15: Quitado | G15: ok | H15: Carol
A16: 10/41548-9 | B16: 592.39 | C16: Abr/25, Maio/25, Junho/25 e Julho/25 | D16: 1ª Parc. Dia 10/09 - Pago (Valor R$ 202,39) 2ª Parc. Dia 21/10 - Pago (Valor R$ 195,00) 3ª Parc. Dia 12/11 - Pago (Valor R$ 195,00) | E16: Pix | F16: Quitado | G16: ok | H16: Carol
A17: 10/1184751-4 | B17: 147.52 | C17: Jul/25 pago em duplicidade | D17: 45904 | E17: Pix | F17: Quitado | G17: ok | H17: Carol
A18: 10/1288241-1 | B18: 387.03 | C18: Abr/25, Maio/25, Jun/25 e Jul/25 | D18: 1ª Parc. Dia 18/09 - Pago (Valor R$ 129,01) 2ª Parc. Dia 09/10 - Pago (Valor R$ 129,01) 3ª Parc. Dia 07/11 - Pago (Valor R$ 129,01) | E18: Pix | F18: Quitado | G18: ok | H18: Carol
A19: 10/2794432-1 | B19: 87.86 | C19: 45778 | D19: 45917 | E19: Pix | G19: ok | H19: Carol
A20: 10/63920-3 | B20: 200.59 | C20: 45778 | D20: 45917 | E20: Pix | F20: Quitado | G20: ok | H20: Carol
A21: 10/384823-1 | B21: 250.43 | C21: Abr/25 e Maio/25 | D21: 45917 | E21: Pix | F21: Quitado | G21: ok | H21: Carol
A22: 10/52987-5 | B22: 45.6 | C22: 45809 | D22: 45918 | E22: Pix | F22: Quitado | G22: ok | H22: Carol
A23: 10/69319-2 | B23: 278.35 | C23: Abril/25 e Junho/25 | D23: 45918 | E23: Pix | F23: Quitado | G23: ok | H23: Carol
A24: 10/1184751-4 | B24: 221.18 | C24: 45778 | D24: 45922 | E24: Pix | F24: Quitado | G24: ok | H24: Carol
A25: 10/61344-8 | B25: 356.23 | C25: 45839 | D25: 45925 | E25: Pix | F25: Quitado | G25: ok | H25: Carol
A26: 10/952579-1 | B26: 124.38 | C26: 45778 | D26: 45925 | E26: Pix | F26: Quitado | G26: ok | H26: Carol
A27: 10/260761-2 | B27: 355.03 | C27: 45778 | D27: 45925 | E27: Pix | F27: Quitado | G27: ok | H27: Carol
A28: 10/226667-4 | B28: 30.62 | C28: 45778 | D28: 45926 | E28: Pix | F28: Quitado | G28: ok | H28: Carol
A29: 10/452884-0 | B29: 98.642704 | C29: Maio/25 pago em duplicidade | D29: 45926 | E29: Pix | F29: Quitado | G29: ok | H29: Carol
A30: 10/8777-5 | B30: 355.68 | C30: 45778 | D30: 45926 | E30: Pix | F30: Quitado | G30: ok | H30: Carol
A31: 10/1081489-5 | B31: 351.64 | C31: 45748 | D31: 45929 | E31: Pix | F31: Quitado | G31: ok | H31: Carol
A32: 10/1081489-5 | B32: 236.57816 | C32: 45809 | D32: 45929 | E32: Pix | F32: Quitado | G32: ok | H32: Carol
A33: 10/395471-6 | B33: 541.04 | C33: Jan/25, Abr/25 e Maio/25 | D33: 45929 | E33: Pix | F33: Quitado | G33: ok | H33: Carol
A34: 10/129490-9 | B34: 200.22 | C34: 45748 | D34: 45930 | E34: Pix | F34: Quitado | G34: ok | H34: Carol
A35: 10/532723-4 | B35: 318.63 | C35: 45748 | D35: 45930 | E35: Pix | F35: Quitado | G35: ok | H35: Carol
A36: 10/129490-9 | B36: 203.2525 | C36: 45839 | D36: 45931 | E36: Pix | F36: Quitado | G36: ok | H36: Carol
A37: 10/276283-9 | B37: 148.43 | C37: 45809 | D37: 45937 | E37: Pix | F37: Quitado | G37: ok | H37: Carol
A38: 10/532081-7 | B38: 311.42 | C38: 45658 | D38: 45938 | E38: Pix | F38: Quitado | G38: ok | H38: Carol
A39: 10/532081-7 | B39: 176.55 | C39: 45748 | D39: 45938 | E39: Pix | F39: Quitado | G39: ok | H39: Carol
A40: 10/156956-5 | B40: 202.72 | C40: 45778 | D40: 45937 | E40: Pix | F40: Quitado | G40: ok | H40: Carol
A41: 10/127464-6 | B41: 300.85 | C41: 45839 | D41: 45930 | E41: Pix | F41: Quitado | G41: ok | H41: Carol
A42: 10/3139326-7 | B42: 351.64 | C42: 45748 | D42: 45932 | E42: Pix | F42: Quitado | G42: ok | H42: Carol
A43: 10/3139326-7 | B43: 300.36919 | C43: 45778 | D43: 45932 | E43: Pix | F43: Quitado | G43: ok | H43: Carol
A44: 10/3139326-7 | B44: 345.41143 | C44: 45870 | D44: 45932 | E44: Pix | F44: Quitado | G44: ok | H44: Carol
A45: 10/1081489-5 | B45: 236.58 | C45: 45809 | D45: 45927 | E45: Pix | F45: Quitado | G45: ok | H45: Carol
... A52: 10/63920-3 | B52: 271.6 | C52: 45870 | D52: 45939 | E52: Pix | F52: Quitado | G52: ok | H52: Carol
A53: 10/341308-5 | B53: 665.2 | C53: Abr/25, Jul/25 e Ago/25 | D53: 1ª Parc. Dia 13/10 - Pago (Valor R$ 300,00) Restante de R$ 32,60 dia 17/10 (R$ 32,60) 2ª Parc. Dia 31/10 - Aguard. Pgmto (Valor R$ 332,60) | E53: Pix | F53: Pendente
A54: 10/1017804-4 | B54: 279.11 | C54: Jul/25 e Ago/25 | D54: 45943 | E54: Pix | F54: Quitado | G54: ok | H54: Carol
A55: 10/3123706-8 | B55: 268.08947 | C55: Agosto | D55: 45950 | E55: Pix | F55: Pendente
A56: 10/395471-6 | B56: 130.66 | C56: 45870 | D56: 45946 | E56: Pix | F56: Quitado | G56: ok | H56: Carol
A57: 10/1433087-2 | B57: 68.92 | C57: 45901 | D57: 45954 | E57: Pix | F57: Quitado | G57: ok | H57: Isabella
A58: 10/511753-6 | B58: 95.43 | C58: 45901 | D58: 45960 | E58: Pix | F58: Quitado | G58: ok | H58: Isabella
A59: 10/142353-2 | B59: 276.06 | C59: 45870 | D59: 45964 | E59: Pix | F59: Quitado | G59: ok | H59: Isabella
A60: 10/3005226-0 | B60: 765.14 | C60: Mar/25 e Mai25 | D60: 45966 | E60: Pix | F60: Quitado | G60: valor encontrado foi de R$765,13 | H60: Isabella
A61: 10/61344-8 | B61: 494.91 | C61: 45901 | D61: 45966 | E61: Pix | F61: Quitado | G61: ok | H61: Isabella
A62: 10/435964-2 | B62: 143.9 | C62: 45901 | D62: 45967 | E62: Pix | F62: Quitado | G62: ok | H62: Isabella
A63: 10/109074-5 | B63: 147.17 | C63: Pago por engano pela cliente, inserido para devolução (ref. set/25) | D63: 45973 | E63: Pix | F63: Quitado | G63: ok | H63: Isabella
A64: 10/41548-9 | B64: 198.68 | C64: 45901 | D64: 45973 | E64: Pix | F64: Quitado | G64: ok | H64: Isabella
A65: 10/41548-9 | B65: 50.97 | C65: 45870 | D65: 45979 | E65: Pix | F65: Quitado | G65: ok | H65: Isabella
A66: 10/41548-9 | B66: 189.68 | C66: 45931 | D66: 45979 | E66: Pix | F66: Quitado | G66: ok | H66: Isabella
A67: 10/341308-5 | B67: 214.04 | C67: 45931 | D67: 45979 | E67: Pix | F67: Quitado Parc. | G67: ok | H67: Isabella
A68: 10/341308-5 | B68: 3.01 | C68: 45931 | D68: 45979 | E68: Pix | F68: Quitado Parc. | G68: ok | H68: Isabella
A69: 10/530195-7 | B69: 53.29 | C69: 45931 | D69: 45987 | E69: Pix | F69: Quitado | G69: ok | H69: Isabella
A70: 10/129490-9 | B70: 196.17 | C70: 45901 | D70: 45971 | E70: Pix | F70: Quitado | G70: ok | H70: Isabella
A71: 10/3040565-8 | B71: 155.33 | C71: 45778 | D71: 45968 | E71: Pix | F71: Quitado | G71: ok | H71: Isabella
A72: 10/1035655-8 | B72: 181.29 | C72: 45778 | D72: 45968 | E72: Pix | F72: Quitado | G72: ok | H72: Isabella
A73: 10/510330-4 | B73: 343.7 | C73: 45931 | D73: 45980 | E73: Pix | F73: Quitado | G73: ok | H73: Isabella
A74: 10/501586-2 | B74: 61.7 | C74: 45931 | D74: 45992 | E74: Pix | F74: Quitado | G74: ok | H74: Isabella
A75: 10/3030784-7 | B75: 496.16 | C75: 45931 | D75: 45992 | E75: Pix | F75: Quitado | G75: ok | H75: Isabella
... A82: 10/466560-0 | B82: 183.42 | C82: 45931 | D82: 45999 | E82: Pix | F82: Quitado | G82: ok | H82: Isabella

Sheet Negociações
A1: INSTALAÇÃO | B1: REFERÊNCIA | C1: VALOR POR REFERÊNCIA | D1: VALOR PAGO | E1: FORMA DE PAGAMENTO | F1: VENCIMENTO PARCELAS | G1: DATA DE PAGAMENTO | H1: STATUS
A2: 10/530195-7 | B2: 45658 | C2: 41.5 | D2: 41.5 | E2: Pix | F2: 45904 | G2: 45904 | H2: Pago
A3: 10/530195-7 | B3: 45748 | C3: 48.78 | D3: 48.78 | E3: Pix
A4: 10/530195-7 | B4: 45778 | C4: 61.11 | D4: 61.11 | E4: Pix | F4: 25/09/2025 | G4: 25/09/2025 | H4: Pago
A5: 10/530195-7 | B5: 45809 | C5: 87.67 | D5: 87.67 | E5: Pix
A6: 10/41548-9 | B6: 45748 | C6: 233.78 | D6: 233.78 | E6: Pix | F6: 45910 | G6: 45910 | H6: Pago
A7: 10/41548-9 | B7: 45778 | C7: 199.219 | D7: 199.219 | E7: Pix | F7: 45951 | G7: 21/10/2025 | H7: Pago
A8: 10/41548-9 | B8: 45809 | C8: 157.39333 | D8: 157.39333 | E8: Pix | F8: 45973 | G8: 45973 | H8: Pago
A9: 10/41548-9 | B9: 45839 | C9: 2 | D9: 2 | E9: Pix
A10: 10/1288241-1 | B10: 45748 | C10: 387.03 | D10: 387.03 | E10: Pix | F10: 45918 | G10: 45918 | H10: Pago
A11: 10/1288241-1 | F11: 45940 | G11: 45939 | H11: Pago
A12: 10/1288241-1 | F12: 45971 | G12: 45968 | H12: Pago
A13: 10/341308-5 | B13: 45748 | C13: 233.62 | D13: 233.62 | E13: Pix | F13: 45943 | G13: 1ª Parc. Dia 13/10/2025 - Pago (Valor R$ 300,00) | H13: Pago
A14: 10/341308-5 | B14: 45839 | C14: 222.24929 | D14: 98.98 | E14: Pix | F14: 45943 | G14: Restante de R$ 32,60 dia 17/10/2025 (R$ 32,60) | H14: Pago
A15: 10/341308-5 | B15: 45870 | C15: 209.332 | F15: 45961 | G15: 31/10/2025 | H15: Atrasado
